Workbook

Sheet PPID Project
A1: S. No. | B1: Project Code | C1: Project Name | D1: Vertical | E1: Project Lead | F1: SPOC | G1: Project Status | H1: Project Start Date (DD/MM/YYYY) | I1: Project End Date (DD/MM/YYYY) | J1: Revised End Date (DD/MM/YYYY) | K1: Client/Department | L1: Client/Ministry | M1: Client Type | N1: Sector/Domain | O1: Sub-Domain | P1: Geographical Coverage | Q1: Nature of Project (TPA/TPE/TPI/TPQA/PMU/PMC/Capacity Building/Impact Assessment) | R1: Internal Stakeholders | S1: External Stakeholders | T1: Project Brief/Objective | U1: Outcomes achieved/Impact created | V1: Award Type | W1: Work Order Value | X1: Proposal | Y1: Project Charter | Z1: Financial Charter | AA1: Bid Filing Documents | AB1: Project Code Generation Requisition Form | AC1: Work Order | AD1: Work orders issued to external stakeholders (if any) | AE1: Work Order Extension | AF1: Revised Financial Charter | AG1: Final Report | AH1: Completion Certificate | AI1: Invoices | AJ1: NOC from Finance Department | AK1: Project Closure Report
A2: 1 | B2: PB00001 | C2: Niti Study | J2: =VLOOKUP(Table1[[#This Row],[Project Code]],'[6]Combined Nov''25'!$E:$O,10,FALSE) -> #N/A | K2: =VLOOKUP(Table1[[#This Row],[Project Code]],'[6]Combined Nov''25'!$E:$K,6,FALSE) -> #N/A | M2: Ministry | N2: =VLOOKUP(Table1[[#This Row],[Project Code]],'[6]Combined Nov''25'!$E:$K,7,FALSE) -> #N/A | O2: Others | P2: Pan India | Q2: Others | T2: =VLOOKUP(Table1[[#This Row],[Project Code]],'[6]Combined Nov''25'!$E:$P,12,FALSE) -> #N/A | U2: #N/A | V2: #N/A | W2: #N/A | X2: No | Y2: No | Z2: No | AA2: No | AB2: No | AC2: No | AD2: No | AE2: No | AF2: No | AG2: No | AH2: No | AI2: No | AJ2: No | AK2: No
A3: 2 | B3: PB00002 | C3: Census of Traders | J3: =VLOOKUP(Table1[[#This Row],[Project Code]],'[6]Combined Nov''25'!$E:$O,10,FALSE) -> #N/A | K3: Department for Promotion of Industry and Internal Trade | L3: Ministry of Commerce and Industry | M3: Ministry | N3: =VLOOKUP(Table1[[#This Row],[Project Code]],'[6]Combined Nov''25'!$E:$K,7,FALSE) -> #N/A | O3: Financial Mgmt, Policy Analysis & Research | P3: Pan India | Q3: Capacity building & Impact Assessment | T3: =VLOOKUP(Table1[[#This Row],[Project Code]],'[6]Combined Nov''25'!$E:$P,12,FALSE) -> #N/A | U3: #N/A | V3: #N/A | W3: #N/A | X3: No | Y3: Yes | Z3: Yes | AA3: No | AB3: No | AC3: Yes | AD3: No | AE3: No | AF3: No | AG3: No | AH3: No | AI3: No | AJ3: No | AK3: No
A4: 3 | B4: PB00003 | C4: E-Commerce Compliance | J4: =VLOOKUP(Table1[[#This Row],[Project Code]],'[6]Combined Nov''25'!$E:$O,10,FALSE) -> #N/A | K4: =VLOOKUP(Table1[[#This Row],[Project Code]],'[6]Combined Nov''25'!$E:$K,6,FALSE) -> #N/A | M4: Ministry | N4: =VLOOKUP(Table1[[#This Row],[Project Code]],'[6]Combined Nov''25'!$E:$K,7,FALSE) -> #N/A | O4: Others | P4: Pan India | Q4: Others | T4: =VLOOKUP(Table1[[#This Row],[Project Code]],'[6]Combined Nov''25'!$E:$P,12,FALSE) -> #N/A | U4: #N/A | V4: #N/A | W4: #N/A | X4: No | Y4: No | Z4: No | AA4: No | AB4: No | AC4: No | AD4: No | AE4: No | AF4: No | AG4: No | AH4: No | AI4: No | AJ4: No | AK4: No
A5: 4 | B5: PB00004 | C5: TPI of buses, depots, workshops & stations of UP | J5: =VLOOKUP(Table1[[#This Row],[Project Code]],'[6]Combined Nov''25'!$E:$O,10,FALSE) -> #N/A | K5: Uttar Pradesh State Road Transport Corporation (UPSRTC) | L5: Government of Uttar Pradesh | M5: 0 | N5: =VLOOKUP(Table1[[#This Row],[Project Code]],'[6]Combined Nov''25'!$E:$K,7,FALSE) -> #N/A | O5: Structural & Utilities Management | P5: Uttar Pradesh | Q5: TPI/TPA/TPE/TPQA | T5: =VLOOKUP(Table1[[#This Row],[Project Code]],'[6]Combined Nov''25'!$E:$P,12,FALSE) -> #N/A | U5: #N/A | V5: #N/A | W5: #N/A | X5: No | Y5: No | Z5: No | AA5: No | AB5: No | AC5: No | AD5: No | AE5: No | AF5: No | AG5: No | AH5: No | AI5: No | AJ5: No | AK5: No
A6: 5 | B6: PB00011 | C6: Sarpanch Samvaad | J6: =VLOOKUP(Table1[[#This Row],[Project Code]],'[6]Combined Nov''25'!$E:$O,10,FALSE) -> #N/A | K6: =VLOOKUP(Table1[[#This Row],[Project Code]],'[6]Combined Nov''25'!$E:$K,6,FALSE) -> #N/A | M6: 0 | N6: =VLOOKUP(Table1[[#This Row],[Project Code]],'[6]Combined Nov''25'!$E:$K,7,FALSE) -> #N/A | O6: Social Welfare, Education & Skill Development | P6: Pan India | Q6: Capacity building & Impact Assessment | T6: =VLOOKUP(Table1[[#This Row],[Project Code]],'[6]Combined Nov''25'!$E:$P,12,FALSE) -> #N/A | U6: #N/A | V6: #N/A | W6: #N/A | X6: No | Y6: No | Z6: No | AA6: No | AB6: No | AC6: No | AD6: No | AE6: No | AF6: No | AG6: No | AH6: No | AI6: No | AJ6: No | AK6: No
A7: 6 | B7: PB00012 | C7: Nashik | D7: PF, P&S | E7: Karan Singh | G7: =VLOOKUP(Table1[[#This Row],[Project Code]],[1]Combined!$E:$I,5,FALSE) -> Ongoing | H7: =VLOOKUP(Table1[[#This Row],[Project Code]],'[2]Combined '!$E:$N,8,FALSE) -> 45075 | K7: Nashik Municipal Corporation | L7: Government of Maharashtra | M7: State Govt. | N7: Sanitaion, Education and Skill development | O7: Water & Sanitation | P7: Maharashtra | Q7: Others | T7: QCI has been engaged by Nashik Municipal Corporation for one of its kind Quality City initiative aiming for situational analysis of different sectors and provide on ground implementation support for several initiatives. | U7: Under the Swachhta Hi Seva Hai initiative, a comprehensive community outreach program was successfully conducted, encompassing a cleanliness drive across four strategic locations and tree plantation at two sites, promoting environmental sustainability. Additionally, an inter-divisional cricket match among Solid Waste Management divisions fostered teamwork and camaraderie, reinforcing the initiative's mission to enhance community engagement, cleanliness, and eco-friendliness. | V7: 0 | W7: N/A | X7: Yes | Z7: Yes | AA7: No | AB7: No | AC7: Yes | AD7: No | AE7: No | AF7: No | AG7: No | AH7: No | AI7: No | AJ7: No | AK7: No
A8: 7 | B8: PB00013 | C8: Trade Surveillance- Leather | J8: =VLOOKUP(Table1[[#This Row],[Project Code]],'[6]Combined Nov''25'!$E:$O,10,FALSE) -> #N/A | K8: =VLOOKUP(Table1[[#This Row],[Project Code]],'[6]Combined Nov''25'!$E:$K,6,FALSE) -> #N/A | M8: 0 | N8: =VLOOKUP(Table1[[#This Row],[Project Code]],'[6]Combined Nov''25'!$E:$K,7,FALSE) -> #N/A | O8: Agriculture, Food Processing & Supply Chain | P8: Pan India | Q8: TPI/TPA/TPE/TPQA | T8: =VLOOKUP(Table1[[#This Row],[Project Code]],'[6]Combined Nov''25'!$E:$P,12,FALSE) -> #N/A | U8: #N/A | V8: #N/A | W8: #N/A | X8: No | Z8: Yes | AA8: No | AB8: Yes | AC8: Yes | AD8: No | AE8: No | AF8: No | AG8: No | AH8: No | AI8: No | AJ8: No | AK8: No
A9: 8 | B9: PB00014 | C9: Quality Assessment of Compressed Bio Gas | D9: T,C,W & E | E9: Dinesh Bhat | G9: Fully Closed | H9: =VLOOKUP(Table1[[#This Row],[Project Code]],'[2]Combined '!$E:$N,8,FALSE) -> 45087 | K9: Banaskantha District Co-op. Milk Producers' Union Ltd. | L9: Cooperative | M9: Cooperative | N9: Bio energy | O9: Mining & Metallurgy | P9: Gujarat | Q9: TPI/TPA/TPE/TPQA | T9: To assess the quality of Biogas getting produced at their Biogas plant located in Palanpur | U9: 1. The Quality Assessment of Biogas marked a pivotal advancement in ensuring the quality of biogas production. The pilot project established a standardized methodology for evaluating biogas quality, with rigorous testing confirming compliance with IS 16087 standards. Sampling and analysis by NABL-accredited laboratories validated high methane content and low impurities. | V9: Nomination | X9: Yes | Y9: No | Z9: No | AA9: No | AB9: No | AC9: Yes | AD9: No | AE9: No | AF9: No | AG9: No | AH9: No | AI9: No | AJ9: No | AK9: No
A10: 9 | B10: PB00015 | C10: Dipstick Assessment for receipt of free grains under PMGKAY | D10: F & H | E10: Ankita Garg | G10: Fully Closed | H10: =VLOOKUP(Table1[[#This Row],[Project Code]],'[2]Combined '!$E:$N,8,FALSE) -> 45055 | K10: =VLOOKUP(Table1[[#This Row],[Project Code]],'[6]Combined Nov''25'!$E:$K,6,FALSE) -> DFPD | L10: Department of Food and Public Distribution | M10: Ministry | N10: Food | O10: Agriculture, Food Processing & Supply Chain | P10: Pan India | Q10: TPI/TPA/TPE/TPQA | T10: Conduct a study about the receipt of free-of-cost food grains under the scheme PMGKAY and beneficiary satisfaction through an on-ground survey. | U10: More than the required feedbacks were collected (nearly 104%) by QCI from across the Indian States/Uts barring six States/UTs namely Odisha, Lakshadweep, Mizoram, Manipur, Chandigarh and Puducherry as either we did not received support from the State or Direct Benefit Transfer (DBT) is applicable or due to civic unrest. The overall result come out to be positive. | V10: Nomination | X10: Yes | Y10: Yes | Z10: No | AA10: No | AB10: No | AC10: No | AD10: Yes | AE10: No | AF10: No | AG10: No | AH10: No | AI10: No | AJ10: No | AK10: No
A11: 10 | B11: PB00016 | C11: TPI of residential building under Rajasthan Housing Board | J11: =VLOOKUP(Table1[[#This Row],[Project Code]],'[6]Combined Nov''25'!$E:$O,10,FALSE) -> #N/A | K11: =VLOOKUP(Table1[[#This Row],[Project Code]],'[6]Combined Nov''25'!$E:$K,6,FALSE) -> #N/A | M11: 0 | N11: =VLOOKUP(Table1[[#This Row],[Project Code]],'[6]Combined Nov''25'!$E:$K,7,FALSE) -> #N/A | O11: Structural & Utilities Management | P11: Rajasthan | Q11: TPI/TPA/TPE/TPQA | T11: =VLOOKUP(Table1[[#This Row],[Project Code]],'[6]Combined Nov''25'!$E:$P,12,FALSE) -> #N/A | U11: #N/A | V11: #N/A | X11: Yes | Y11: No | Z11: Yes | AA11: No | AB11: Yes | AC11: Yes | AD11: No | AE11: No | AF11: No | AG11: No | AH11: No | AI11: No | AJ11: No | AK11: No
A12: 11 | B12: PB00017 | C12: SILF | D12: Infra | E12: Shailja Devgan | G12: Fully Closed | H12: =VLOOKUP(Table1[[#This Row],[Project Code]],'[2]Combined '!$E:$N,8,FALSE) -> 44938 | K12: =VLOOKUP(Table1[[#This Row],[Project Code]],'[6]Combined Nov''25'!$E:$K,6,FALSE) -> SILF | L12: Sasakawa-India Leprosy Foundation. | M12: Non-Profit Organisation | N12: Social Impact | O12: Social Welfare, Education & Skill Development | P12: Pan India | Q12: Capacity building & Impact Assessment | T12: To conduct an impact evaluation of the livelihoods project in the Champa district of Chhattisgarh which will analyze the impact of the project on the lives of the beneficiaries and their family members, any substantive change in their socio-economic standing. | U12: Narrative analysis questionniare been developed and interviews conducted for beneficiaries who received funds from SILF to understand the in-depth impact. The final report with analysis has been submitted. | V12: 0 | W12: 246400 | X12: Yes | Y12: No | Z12: Yes | AA12: No | AB12: No | AC12: No | AD12: No | AE12: No | AF12: No | AG12: Yes | AH12: No | AI12: No | AJ12: No | AK12: No
A13: 12 | B13: PB00018 | C13: Culture_National Library_2024 | D13: T,C,W & E | E13: Prakhar Joshi | G13: Fully Closed | H13: =VLOOKUP(Table1[[#This Row],[Project Code]],'[2]Combined '!$E:$N,8,FALSE) -> 45383 | K13: =VLOOKUP(Table1[[#This Row],[Project Code]],'[6]Combined Nov''25'!$E:$K,6,FALSE) -> Ministry of Culture | L13: Ministry of Culture | M13: Ministry | N13: Arts, Culture & Heritage | O13: Arts, Culture & Tourism | P13: Pan India | Q13: Capacity building & Impact Assessment | T13: The National Library functions as a Subordinative Office of the Ministry of Culture, Government of India. As part of Phase-1 Study of Organizations & Central Sector Schemes of the Ministry of Culture, QCI had outlined broad recommendations for the National Library. | U13: Restoration of 25% of the workforce at the National Library Designing structure of a proposed digital department that can effectively help preserve 2+ million books Developed detailed KRAs of 500+ posts at the National Library | V13: Nomination | W13: 0 | Y13: No | Z13: No | AA13: No | AB13: No | AC13: Yes | AD13: No | AE13: No | AF13: No | AG13: No | AH13: No | AI13: No | AJ13: No | AK13: No
A14: 13 | B14: PB00019 | C14: Assessment, Capacity Building & Certification of SST | D14: T,C,W & E | E14: Dinesh Bhat | G14: =VLOOKUP(Table1[[#This Row],[Project Code]],[1]Combined!$E:$I,5,FALSE) -> Ongoing | H14: =VLOOKUP(Table1[[#This Row],[Project Code]],'[2]Combined '!$E:$N,8,FALSE) -> 45385 | K14: =VLOOKUP(Table1[[#This Row],[Project Code]],'[6]Combined Nov''25'!$E:$K,6,FALSE) -> Shri Somnath Trust | L14: Shri Somnath Trust | M14: Independent Body | N14: Tourism | O14: Arts, Culture & Tourism | P14: Gujarat | Q14: Capacity building & Impact Assessment | T14: The National Library then requested QCI to undertake a detailed review of its existing manpower, structure and governance models, and activities and make suggestions for changes. QCI reviewed the institution in detail: including their current recruitment rules, Staff Inspection Unit Report, and other previous reports highlighting human resource related issues of the National Library, governance, structure, objective and mandate. In order to understand the landscape further, QCI also studied organizational structures and hierarchy models of leading global libraries. | U14: The impact extends beyond technical compliance. Enhanced biogas quality supports national clean energy goals, reduces dependence on fossil fuels, and mitigates greenhouse gas emissions. It also leads to improved energy efficiency, lower operational costs, and strengthened sustainability efforts | V14: Nomination | W14: 0 | Y14: No | Z14: No | AA14: No | AB14: No | AC14: No | AD14: No | AE14: No | AF14: No | AG14: No | AH14: No | AI14: No | AJ14: No | AK14: No
A15: 14 | B15: PP00001 | C15: Third Party Sampling, Testing & Analysis of Coal | D15: NR | E15: Abhishek Mazumdar | G15: =VLOOKUP(Table1[[#This Row],[Project Code]],[1]Combined!$E:$I,5,FALSE) -> Ongoing | H15: =VLOOKUP(Table1[[#This Row],[Project Code]],'[2]Combined '!$E:$N,8,FALSE) -> 42881 | K15: =VLOOKUP(Table1[[#This Row],[Project Code]],'[6]Combined Nov''25'!$E:$K,6,FALSE) -> Coal India Limited | L15: Coal India Limited | M15: PSU | N15: Coal | O15: Mining & Metallurgy | P15: Pan India | Q15: TPI/TPA/TPE/TPQA | T15: Collection, preparation and analysis of coal at loading points for non- power consumers and power sector consumers | U15: QCI has executed around 4,770+ tripartite agreements among the coal companies and 370+ coal consumers for facilitating the Third Party Sampling of coal (TPS). QCI has commenced it’s operations at 320+ loading/dispatch points across the CIL subsidiaries. More than 707.27 Million Metric Tonnes of coal has been sampled since the inception and analysis results submitted within the 15 working days as per the service level agreement. | V15: Nomination | W15: 0 | Y15: No | Z15: No | AA15: No | AB15: No | AC15: No | AD15: No | AE15: No | AF15: No | AG15: No | AH15: No | AI15: No | AJ15: No | AK15: No
A16: 15 | B16: PP00002 | C16: SBM ODF, ODF+, ODF++ | J16: =VLOOKUP(Table1[[#This Row],[Project Code]],'[6]Combined Nov''25'!$E:$O,10,FALSE) -> #N/A | K16: =VLOOKUP(Table1[[#This Row],[Project Code]],'[6]Combined Nov''25'!$E:$K,6,FALSE) -> #N/A | L16: Ministry of Housing and Urban Affairs | M16: Ministry | N16: =VLOOKUP(Table1[[#This Row],[Project Code]],'[6]Combined Nov''25'!$E:$K,7,FALSE) -> #N/A | O16: Water & Sanitation | P16: Pan India | Q16: TPI/TPA/TPE/TPQA | T16: =VLOOKUP(Table1[[#This Row],[Project Code]],'[6]Combined Nov''25'!$E:$P,12,FALSE) -> #N/A | U16: #N/A | V16: #N/A | W16: #N/A | X16: No | Y16: No | Z16: Yes | AA16: No | AB16: Yes | AC16: Yes | AD16: No | AE16: No | AF16: No | AG16: No | AH16: No | AI16: No | AJ16: No | AK16: No
A17: 16 | B17: PP00003 | C17: MoUD - Star Rating | J17: =VLOOKUP(Table1[[#This Row],[Project Code]],'[6]Combined Nov''25'!$E:$O,10,FALSE) -> #N/A | K17: =VLOOKUP(Table1[[#This Row],[Project Code]],'[6]Combined Nov''25'!$E:$K,6,FALSE) -> #N/A | L17: Ministry of Housing and Urban Affairs | M17: Ministry | N17: =VLOOKUP(Table1[[#This Row],[Project Code]],'[6]Combined Nov''25'!$E:$K,7,FALSE) -> #N/A | O17: Water & Sanitation | P17: Pan India | Q17: TPI/TPA/TPE/TPQA | T17: =VLOOKUP(Table1[[#This Row],[Project Code]],'[6]Combined Nov''25'!$E:$P,12,FALSE) -> #N/A | U17: #N/A | V17: #N/A | W17: #N/A | Y17: No | Z17: No | AA17: No | AB17: No | AC17: No | AD17: No | AE17: No | AF17: No | AG17: No | AH17: No | AI17: No | AJ17: No | AK17: No
A18: 17 | B18: PP00004 | C18: TPI of 97 Ganga Towns | J18: =VLOOKUP(Table1[[#This Row],[Project Code]],'[6]Combined Nov''25'!$E:$O,10,FALSE) -> #N/A | K18: =VLOOKUP(Table1[[#This Row],[Project Code]],'[6]Combined Nov''25'!$E:$K,6,FALSE) -> #N/A | L18: Ministry of Housing and Urban Affairs | M18: Ministry | N18: =VLOOKUP(Table1[[#This Row],[Project Code]],'[6]Combined Nov''25'!$E:$K,7,FALSE) -> #N/A | O18: Water & Sanitation | P18: Pan India | Q18: TPI/TPA/TPE/TPQA | T18: =VLOOKUP(Table1[[#This Row],[Project Code]],'[6]Combined Nov''25'!$E:$P,12,FALSE) -> #N/A | U18: #N/A | V18: #N/A | W18: #N/A | Y18: No | Z18: No | AA18: No | AB18: No | AC18: No | AD18: No | AE18: No | AF18: No | AG18: No | AH18: No | AI18: No | AJ18: No | AK18: No
A19: 18 | B19: PP00005 | C19: IDFOI Assessment | J19: =VLOOKUP(Table1[[#This Row],[Project Code]],'[6]Combined Nov''25'!$E:$O,10,FALSE) -> #N/A | K19: IBF-OI | L19: Govt Body (Not for Profit) | M19: Ministry | N19: =VLOOKUP(Table1[[#This Row],[Project Code]],'[6]Combined Nov''25'!$E:$K,7,FALSE) -> #N/A | O19: Financial Mgmt, Policy Analysis & Research | P19: Pan India | Q19: TPI/TPA/TPE/TPQA | T19: =VLOOKUP(Table1[[#This Row],[Project Code]],'[6]Combined Nov''25'!$E:$P,12,FALSE) -> #N/A | U19: #N/A | V19: #N/A | W19: #N/A | Y19: No | Z19: No | AA19: No | AB19: No | AC19: No | AD19: No | AE19: No | AF19: No | AG19: No | AH19: No | AI19: No | AJ19: No | AK19: No
A20: 19 | B20: PP00006 | C20: Swachh RO | J20: =VLOOKUP(Table1[[#This Row],[Project Code]],'[6]Combined Nov''25'!$E:$O,10,FALSE) -> #N/A | K20: =VLOOKUP(Table1[[#This Row],[Project Code]],'[6]Combined Nov''25'!$E:$K,6,FALSE) -> #N/A | L20: HPCL | M20: PSU | N20: =VLOOKUP(Table1[[#This Row],[Project Code]],'[6]Combined Nov''25'!$E:$K,7,FALSE) -> #N/A | O20: Water & Sanitation | P20: Pan India | Q20: TPI/TPA/TPE/TPQA | T20: =VLOOKUP(Table1[[#This Row],[Project Code]],'[6]Combined Nov''25'!$E:$P,12,FALSE) -> #N/A | U20: #N/A | V20: #N/A | W20: #N/A | X20: No | Y20: No | Z20: No | AA20: No | AB20: No | AC20: No | AD20: No | AE20: No | AF20: No | AG20: No | AH20: No | AI20: No | AJ20: No | AK20: No
A21: 20 | B21: PP00007 | C21: Madhya Pradesh PIU | J21: =VLOOKUP(Table1[[#This Row],[Project Code]],'[6]Combined Nov''25'!$E:$O,10,FALSE) -> #N/A | K21: =VLOOKUP(Table1[[#This Row],[Project Code]],'[6]Combined Nov''25'!$E:$K,6,FALSE) -> #N/A | L21: Government of Madhya Pradesh | M21: State Govt. | N21: =VLOOKUP(Table1[[#This Row],[Project Code]],'[6]Combined Nov''25'!$E:$K,7,FALSE) -> #N/A | O21: Water & Sanitation | P21: Madhya Pradesh | Q21: Capacity building & Impact Assessment | T21: =VLOOKUP(Table1[[#This Row],[Project Code]],'[6]Combined Nov''25'!$E:$P,12,FALSE) -> #N/A | U21: #N/A | V21: #N/A | W21: #N/A | X21: No | Y21: Yes | Z21: No | AA21: No | AB21: No | AC21: No | AD21: No | AE21: No | AF21: No | AG21: No | AH21: No | AI21: No | AJ21: No | AK21: No
A22: 21 | B22: PP00008 | C22: Gwalior PIU | J22: =VLOOKUP(Table1[[#This Row],[Project Code]],'[6]Combined Nov''25'!$E:$O,10,FALSE) -> #N/A | K22: Municipal Corporation of Gwalior | L22: Government of Madhya Pradesh | M22: State Govt. | N22: =VLOOKUP(Table1[[#This Row],[Project Code]],'[6]Combined Nov''25'!$E:$K,7,FALSE) -> #N/A | O22: Water & Sanitation | P22: Madhya Pradesh | Q22: Capacity building & Impact Assessment | T22: =VLOOKUP(Table1[[#This Row],[Project Code]],'[6]Combined Nov''25'!$E:$P,12,FALSE) -> #N/A | U22: #N/A | V22: #N/A | W22: #N/A | X22: Yes | Y22: Yes | Z22: Yes | AA22: No | AB22: Yes | AC22: Yes | AD22: Yes | AE22: No | AF22: No | AG22: Yes | AH22: No | AI22: No | AJ22: No | AK22: No
A23: 22 | B23: PP00009 | C23: Swastha Pradesh Swachh Pradesh | J23: =VLOOKUP(Table1[[#This Row],[Project Code]],'[6]Combined Nov''25'!$E:$O,10,FALSE) -> #N/A | K23: =VLOOKUP(Table1[[#This Row],[Project Code]],'[6]Combined Nov''25'!$E:$K,6,FALSE) -> #N/A | L23: Government of Madhya Pradesh | M23: State Govt. | N23: =VLOOKUP(Table1[[#This Row],[Project Code]],'[6]Combined Nov''25'!$E:$K,7,FALSE) -> #N/A | O23: Water & Sanitation | P23: Madhya Pradesh | Q23: TPI/TPA/TPE/TPQA | T23: =VLOOKUP(Table1[[#This Row],[Project Code]],'[6]Combined Nov''25'!$E:$P,12,FALSE) -> #N/A | U23: #N/A | V23: #N/A | W23: #N/A | X23: No | Y23: No | Z23: No | AA23: No | AB23: No | AC23: No | AD23: No | AE23: No | AF23: No | AG23: No | AH23: No | AI23: No | AJ23: No | AK23: No
A24: 23 | B24: PP00010 | C24: Delhi Toilet Survey | J24: =VLOOKUP(Table1[[#This Row],[Project Code]],'[6]Combined Nov''25'!$E:$O,10,FALSE) -> #N/A | K24: =VLOOKUP(Table1[[#This Row],[Project Code]],'[6]Combined Nov''25'!$E:$K,6,FALSE) -> #N/A | L24: Ministry of Housing and Urban Affairs | M24: Ministry | N24: =VLOOKUP(Table1[[#This Row],[Project Code]],'[6]Combined Nov''25'!$E:$K,7,FALSE) -> #N/A | O24: Water & Sanitation | P24: NCT of Delhi | Q24: TPI/TPA/TPE/TPQA | T24: =VLOOKUP(Table1[[#This Row],[Project Code]],'[6]Combined Nov''25'!$E:$P,12,FALSE) -> #N/A | U24: #N/A | V24: #N/A | W24: #N/A | X24: No | Y24: No | Z24: Yes | AA24: Yes | AB24: Yes | AC24: Yes | AD24: No | AE24: No | AF24: No | AG24: No | AH24: No | AI24: No | AJ24: No | AK24: No
A25: 24 | B25: PP00011 | C25: Google Toilet Mapping | J25: =VLOOKUP(Table1[[#This Row],[Project Code]],'[6]Combined Nov''25'!$E:$O,10,FALSE) -> #N/A | K25: =VLOOKUP(Table1[[#This Row],[Project Code]],'[6]Combined Nov''25'!$E:$K,6,FALSE) -> #N/A | L25: Ministry of Housing and Urban Affairs | M25: Ministry | N25: =VLOOKUP(Table1[[#This Row],[Project Code]],'[6]Combined Nov''25'!$E:$K,7,FALSE) -> #N/A | O25: Water & Sanitation | P25: Pan India | Q25: TPI/TPA/TPE/TPQA | T25: =VLOOKUP(Table1[[#This Row],[Project Code]],'[6]Combined Nov''25'!$E:$P,12,FALSE) -> #N/A | U25: #N/A | V25: #N/A | W25: #N/A | X25: Yes | Y25: Yes | Z25: Yes | AA25: No | AB25: No | AC25: Yes | AD25: Yes | AE25: No | AF25: No | AG25: Yes | AH25: No | AI25: No | AJ25: No | AK25: No
A26: 25 | B26: PP00012 | C26: SBM Jharkhand | J26: =VLOOKUP(Table1[[#This Row],[Project Code]],'[6]Combined Nov''25'!$E:$O,10,FALSE) -> #N/A | K26: =VLOOKUP(Table1[[#This Row],[Project Code]],'[6]Combined Nov''25'!$E:$K,6,FALSE) -> #N/A | L26: Government of Jharkhand | M26: State Govt. | N26: =VLOOKUP(Table1[[#This Row],[Project Code]],'[6]Combined Nov''25'!$E:$K,7,FALSE) -> #N/A | O26: Water & Sanitation | P26: Jharkhand | Q26: TPI/TPA/TPE/TPQA | T26: =VLOOKUP(Table1[[#This Row],[Project Code]],'[6]Combined Nov''25'!$E:$P,12,FALSE) -> #N/A | U26: #N/A | V26: #N/A | W26: #N/A | X26: Yes | Y26: Yes | Z26: Yes | AA26: No | AB26: No | AC26: Yes | AD26: No | AE26: No | AF26: No | AG26: Yes | AH26: No | AI26: No | AJ26: No | AK26: No
A27: 26 | B27: PP00013 | C27: Swachh Rail 2018 | J27: =VLOOKUP(Table1[[#This Row],[Project Code]],'[6]Combined Nov''25'!$E:$O,10,FALSE) -> #N/A | K27: =VLOOKUP(Table1[[#This Row],[Project Code]],'[6]Combined Nov''25'!$E:$K,6,FALSE) -> #N/A | L27: Ministry of Railways | M27: Ministry | N27: =VLOOKUP(Table1[[#This Row],[Project Code]],'[6]Combined Nov''25'!$E:$K,7,FALSE) -> #N/A | O27: Water & Sanitation | P27: Pan India | Q27: TPI/TPA/TPE/TPQA | T27: =VLOOKUP(Table1[[#This Row],[Project Code]],'[6]Combined Nov''25'!$E:$P,12,FALSE) -> #N/A | U27: #N/A | V27: #N/A | W27: #N/A | X27: No | Y27: No | Z27: No | AA27: No | AB27: No | AC27: Yes | AD27: No | AE27: No | AF27: No | AG27: No | AH27: No | AI27: No | AJ27: No | AK27: No
A28: 27 | B28: PP00014 | C28: SBM Telangana | J28: =VLOOKUP(Table1[[#This Row],[Project Code]],'[6]Combined Nov''25'!$E:$O,10,FALSE) -> #N/A | K28: =VLOOKUP(Table1[[#This Row],[Project Code]],'[6]Combined Nov''25'!$E:$K,6,FALSE) -> #N/A | L28: Government of Telangana | M28: State Govt. | N28: =VLOOKUP(Table1[[#This Row],[Project Code]],'[6]Combined Nov''25'!$E:$K,7,FALSE) -> #N/A | O28: Water & Sanitation | P28: Telangana | Q28: TPI/TPA/TPE/TPQA | T28: =VLOOKUP(Table1[[#This Row],[Project Code]],'[6]Combined Nov''25'!$E:$P,12,FALSE) -> #N/A | U28: #N/A | V28: #N/A | W28: #N/A | X28: No | Y28: No | Z28: No | AA28: No | AB28: No | AC28: No | AD28: No | AE28: No | AF28: No | AG28: No | AH28: No | AI28: No | AJ28: No | AK28: No
A29: 28 | B29: PP00015 | C29: SBM Gujarat Yatradham | J29: =VLOOKUP(Table1[[#This Row],[Project Code]],'[6]Combined Nov''25'!$E:$O,10,FALSE) -> #N/A | K29: Tourism Corporation of Gujarat Limited | L29: Government of Gujarat | M29: State Govt. | N29: =VLOOKUP(Table1[[#This Row],[Project Code]],'[6]Combined Nov''25'!$E:$K,7,FALSE) -> #N/A | O29: Water & Sanitation | P29: Gujarat | Q29: TPI/TPA/TPE/TPQA | T29: =VLOOKUP(Table1[[#This Row],[Project Code]],'[6]Combined Nov''25'!$E:$P,12,FALSE) -> #N/A | U29: #N/A | V29: #N/A | W29: #N/A | X29: No | Y29: No | Z29: No | AA29: No | AB29: No | AC29: No | AD29: No | AE29: No | AF29: No | AG29: No | AH29: No | AI29: No | AJ29: No | AK29: No
A30: 29 | B30: PP00016 | C30: SBM Gujarat Tourism | J30: =VLOOKUP(Table1[[#This Row],[Project Code]],'[6]Combined Nov''25'!$E:$O,10,FALSE) -> #N/A | K30: Tourism Corporation of Gujarat Limited | L30: Government of Gujarat | M30: State Govt. | N30: =VLOOKUP(Table1[[#This Row],[Project Code]],'[6]Combined Nov''25'!$E:$K,7,FALSE) -> #N/A | O30: Water & Sanitation | P30: Gujarat | Q30: TPI/TPA/TPE/TPQA | T30: =VLOOKUP(Table1[[#This Row],[Project Code]],'[6]Combined Nov''25'!$E:$P,12,FALSE) -> #N/A | U30: #N/A | V30: #N/A | W30: #N/A | X30: No | Y30: No | Z30: No | AA30: No | AB30: No | AC30: No | AD30: No | AE30: No | AF30: No | AG30: No | AH30: No | AI30: No | AJ30: No | AK30: No
A31: 30 | B31: PP00017 | C31: Statue of Unity | J31: =VLOOKUP(Table1[[#This Row],[Project Code]],'[6]Combined Nov''25'!$E:$O,10,FALSE) -> #N/A | K31: Tourism Corporation of Gujarat Limited | L31: Government of Gujarat | M31: State Govt. | N31: =VLOOKUP(Table1[[#This Row],[Project Code]],'[6]Combined Nov''25'!$E:$K,7,FALSE) -> #N/A | O31: Structural & Utilities Management | P31: Gujarat | Q31: TPI/TPA/TPE/TPQA | T31: =VLOOKUP(Table1[[#This Row],[Project Code]],'[6]Combined Nov''25'!$E:$P,12,FALSE) -> #N/A | U31: #N/A | V31: #N/A | W31: #N/A | X31: Yes | Y31: Yes | Z31: Yes | AA31: Yes | AB31: Yes | AC31: Yes | AD31: No | AE31: No | AF31: No | AG31: No | AH31: No | AI31: No | AJ31: No | AK31: No
A32: 31 | B32: PP00018 | C32: SBM Rural UP | J32: =VLOOKUP(Table1[[#This Row],[Project Code]],'[6]Combined Nov''25'!$E:$O,10,FALSE) -> #N/A | K32: Department of Panchayati Raj | L32: Government of Uttar Pradesh | M32: State Govt. | N32: =VLOOKUP(Table1[[#This Row],[Project Code]],'[6]Combined Nov''25'!$E:$K,7,FALSE) -> #N/A | O32: Water & Sanitation | P32: Uttar Pradesh | Q32: TPI/TPA/TPE/TPQA | T32: =VLOOKUP(Table1[[#This Row],[Project Code]],'[6]Combined Nov''25'!$E:$P,12,FALSE) -> #N/A | U32: #N/A | V32: #N/A | W32: #N/A | X32: Yes | Y32: Yes | Z32: Yes | AA32: No | AB32: Yes | AC32: Yes | AD32: Yes | AE32: No | AF32: No | AG32: No | AH32: No | AI32: No | AJ32: No | AK32: No
A33: 32 | B33: PP00019 | C33: Swachh NDMC | J33: =VLOOKUP(Table1[[#This Row],[Project Code]],'[6]Combined Nov''25'!$E:$O,10,FALSE) -> #N/A | K33: New Delhi Municipal Council | L33: Government of NCT of Delhi | M33: State Govt. | N33: =VLOOKUP(Table1[[#This Row],[Project Code]],'[6]Combined Nov''25'!$E:$K,7,FALSE) -> #N/A | O33: Water & Sanitation | P33: NCT of Delhi | Q33: TPI/TPA/TPE/TPQA | T33: =VLOOKUP(Table1[[#This Row],[Project Code]],'[6]Combined Nov''25'!$E:$P,12,FALSE) -> #N/A | U33: #N/A | V33: #N/A | W33: #N/A | X33: Yes | Y33: No | Z33: Yes | AA33: Yes | AB33: Yes | AC33: Yes | AD33: No | AE33: No | AF33: No | AG33: No | AH33: No | AI33: No | AJ33: No | AK33: No
A34: 33 | B34: PP00020 | C34: ALF Swachhta Award Ranking | J34: =VLOOKUP(Table1[[#This Row],[Project Code]],'[6]Combined Nov''25'!$E:$O,10,FALSE) -> #N/A | K34: =VLOOKUP(Table1[[#This Row],[Project Code]],'[6]Combined Nov''25'!$E:$K,6,FALSE) -> #N/A | L34: Ministry of Housing and Urban Affairs | M34: Ministry | N34: =VLOOKUP(Table1[[#This Row],[Project Code]],'[6]Combined Nov''25'!$E:$K,7,FALSE) -> #N/A | O34: Governanace, Administration & Digital Infrastructure | P34: Pan India | Q34: Capacity building & Impact Assessment | T34: =VLOOKUP(Table1[[#This Row],[Project Code]],'[6]Combined Nov''25'!$E:$P,12,FALSE) -> #N/A | U34: #N/A | V34: #N/A | W34: #N/A | X34: Yes | Y34: Yes | Z34: Yes | AA34: No | AB34: Yes | AC34: Yes | AD34: No | AE34: No | AF34: No | AG34: No | AH34: No | AI34: No | AJ34: No | AK34: No
A35: 34 | B35: PP00021 | C35: Power Urban | J35: =VLOOKUP(Table1[[#This Row],[Project Code]],'[6]Combined Nov''25'!$E:$O,10,FALSE) -> #N/A | K35: =VLOOKUP(Table1[[#This Row],[Project Code]],'[6]Combined Nov''25'!$E:$K,6,FALSE) -> #N/A | L35: Ministry of Power | M35: Ministry | N35: =VLOOKUP(Table1[[#This Row],[Project Code]],'[6]Combined Nov''25'!$E:$K,7,FALSE) -> #N/A | O35: Structural & Utilities Management | P35: Pan India | Q35: TPI/TPA/TPE/TPQA | T35: =VLOOKUP(Table1[[#This Row],[Project Code]],'[6]Combined Nov''25'!$E:$P,12,FALSE) -> #N/A | U35: #N/A | V35: #N/A | W35: #N/A | X35: Yes | Y35: Yes | Z35: Yes | AA35: No | AB35: Yes | AC35: Yes | AD35: Yes | AE35: No | AF35: No | AG35: No | AH35: No | AI35: No | AJ35: No | AK35: No
A36: 35 | B36: PP00022 | C36: Power Rural 2018 | J36: =VLOOKUP(Table1[[#This Row],[Project Code]],'[6]Combined Nov''25'!$E:$O,10,FALSE) -> #N/A | K36: =VLOOKUP(Table1[[#This Row],[Project Code]],'[6]Combined Nov''25'!$E:$K,6,FALSE) -> #N/A | L36: Ministry of Power | M36: Ministry | N36: =VLOOKUP(Table1[[#This Row],[Project Code]],'[6]Combined Nov''25'!$E:$K,7,FALSE) -> #N/A | O36: Structural & Utilities Management | P36: Pan India | Q36: TPI/TPA/TPE/TPQA | T36: =VLOOKUP(Table1[[#This Row],[Project Code]],'[6]Combined Nov''25'!$E:$P,12,FALSE) -> #N/A | U36: #N/A | V36: #N/A | W36: #N/A | X36: No | Y36: No | Z36: No | AA36: No | AB36: No | AC36: No | AD36: No | AE36: No | AF36: No | AG36: No | AH36: No | AI36: No | AJ36: No | AK36: No
A37: 36 | B37: PP00023 | C37: MoPNG - PMU | J37: =VLOOKUP(Table1[[#This Row],[Project Code]],'[6]Combined Nov''25'!$E:$O,10,FALSE) -> #N/A | K37: =VLOOKUP(Table1[[#This Row],[Project Code]],'[6]Combined Nov''25'!$E:$K,6,FALSE) -> #N/A | L37: Ministry of Petroleum and Natural Gas | M37: Ministry | N37: =VLOOKUP(Table1[[#This Row],[Project Code]],'[6]Combined Nov''25'!$E:$K,7,FALSE) -> #N/A | O37: Governanace, Administration & Digital Infrastructure | P37: Pan India | Q37: PMU/PMC | T37: =VLOOKUP(Table1[[#This Row],[Project Code]],'[6]Combined Nov''25'!$E:$P,12,FALSE) -> #N/A | U37: #N/A | V37: #N/A | W37: #N/A | X37: Yes | Y37: Yes | Z37: Yes | AA37: No | AB37: Yes | AC37: Yes | AD37: Yes | AE37: No | AF37: No | AG37: No | AH37: No | AI37: No | AJ37: No | AK37: No
A38: 37 | B38: PP00024 | C38: DARPG- Citizen's Charter | J38: =VLOOKUP(Table1[[#This Row],[Project Code]],'[6]Combined Nov''25'!$E:$O,10,FALSE) -> #N/A | K38: =VLOOKUP(Table1[[#This Row],[Project Code]],'[6]Combined Nov''25'!$E:$K,6,FALSE) -> #N/A | L38: Department of Administrative Reforms and Public Grievances | M38: Ministry | N38: =VLOOKUP(Table1[[#This Row],[Project Code]],'[6]Combined Nov''25'!$E:$K,7,FALSE) -> #N/A | O38: Governanace, Administration & Digital Infrastructure | P38: Pan India | Q38: Capacity building & Impact Assessment | T38: =VLOOKUP(Table1[[#This Row],[Project Code]],'[6]Combined Nov''25'!$E:$P,12,FALSE) -> #N/A | U38: #N/A | V38: #N/A | W38: #N/A | X38: Yes | Y38: No | Z38: No | AA38: No | AB38: No | AC38: No | AD38: No | AE38: No | AF38: No | AG38: No | AH38: No | AI38: No | AJ38: No | AK38: No
A39: 38 | B39: PP00025 | C39: DARPG- eOffice | J39: =VLOOKUP(Table1[[#This Row],[Project Code]],'[6]Combined Nov''25'!$E:$O,10,FALSE) -> #N/A | K39: =VLOOKUP(Table1[[#This Row],[Project Code]],'[6]Combined Nov''25'!$E:$K,6,FALSE) -> #N/A | L39: Department of Administrative Reforms and Public Grievances | M39: Ministry | N39: =VLOOKUP(Table1[[#This Row],[Project Code]],'[6]Combined Nov''25'!$E:$K,7,FALSE) -> #N/A | O39: Governanace, Administration & Digital Infrastructure | P39: Pan India | Q39: PMU/PMC | T39: =VLOOKUP(Table1[[#This Row],[Project Code]],'[6]Combined Nov''25'!$E:$P,12,FALSE) -> #N/A | U39: #N/A | V39: #N/A | W39: #N/A | X39: No | Y39: No | Z39: No | AA39: No | AB39: No | AC39: No | AD39: No | AE39: No | AF39: No | AG39: No | AH39: No | AI39: No | AJ39: No | AK39: No
A40: 39 | B40: PP00026 | C40: DARPG - Dashboard Extension | J40: =VLOOKUP(Table1[[#This Row],[Project Code]],'[6]Combined Nov''25'!$E:$O,10,FALSE) -> #N/A | K40: =VLOOKUP(Table1[[#This Row],[Project Code]],'[6]Combined Nov''25'!$E:$K,6,FALSE) -> #N/A | L40: Department of Administrative Reforms and Public Grievances | M40: Ministry | N40: =VLOOKUP(Table1[[#This Row],[Project Code]],'[6]Combined Nov''25'!$E:$K,7,FALSE) -> #N/A | O40: Governanace, Administration & Digital Infrastructure | P40: Pan India | Q40: Capacity building & Impact Assessment | T40: =VLOOKUP(Table1[[#This Row],[Project Code]],'[6]Combined Nov''25'!$E:$P,12,FALSE) -> #N/A | U40: #N/A | V40: #N/A | W40: #N/A | X40: No | Y40: Yes | Z40: Yes | AA40: No | AB40: Yes | AC40: Yes | AD40: No | AE40: No | AF40: No | AG40: No | AH40: No | AI40: No | AJ40: No | AK40: No
A41: 40 | B41: PP00027 | C41: MoRTH - Highway Rating | J41: =VLOOKUP(Table1[[#This Row],[Project Code]],'[6]Combined Nov''25'!$E:$O,10,FALSE) -> #N/A | K41: =VLOOKUP(Table1[[#This Row],[Project Code]],'[6]Combined Nov''25'!$E:$K,6,FALSE) -> #N/A | L41: Ministry of Road Transport and Highways | M41: Ministry | N41: =VLOOKUP(Table1[[#This Row],[Project Code]],'[6]Combined Nov''25'!$E:$K,7,FALSE) -> #N/A | O41: Governanace, Administration & Digital Infrastructure | P41: Pan India | Q41: TPI/TPA/TPE/TPQA | T41: =VLOOKUP(Table1[[#This Row],[Project Code]],'[6]Combined Nov''25'!$E:$P,12,FALSE) -> #N/A | U41: #N/A | V41: #N/A | W41: #N/A | X41: Yes | Y41: Yes | Z41: Yes | AA41: No | AB41: Yes | AC41: Yes | AD41: No | AE41: No | AF41: No | AG41: No | AH41: No | AI41: No | AJ41: No | AK41: No
A42: 41 | B42: PP00028 | C42: MoRTH - Awards 2018 | J42: =VLOOKUP(Table1[[#This Row],[Project Code]],'[6]Combined Nov''25'!$E:$O,10,FALSE) -> #N/A | K42: =VLOOKUP(Table1[[#This Row],[Project Code]],'[6]Combined Nov''25'!$E:$K,6,FALSE) -> #N/A | L42: Ministry of Road Transport and Highways | M42: Ministry | N42: =VLOOKUP(Table1[[#This Row],[Project Code]],'[6]Combined Nov''25'!$E:$K,7,FALSE) -> #N/A | O42: Governanace, Administration & Digital Infrastructure | P42: Pan India | Q42: Capacity building & Impact Assessment | T42: =VLOOKUP(Table1[[#This Row],[Project Code]],'[6]Combined Nov''25'!$E:$P,12,FALSE) -> #N/A | U42: #N/A | V42: #N/A | W42: #N/A | X42: No | Y42: No | Z42: Yes | AA42: No | AB42: Yes | AC42: Yes | AD42: No | AE42: No | AF42: No | AG42: No | AH42: No | AI42: No | AJ42: No | AK42: No
A43: 42 | B43: PP00029 | C43: Tourism Study | J43: =VLOOKUP(Table1[[#This Row],[Project Code]],'[6]Combined Nov''25'!$E:$O,10,FALSE) -> #N/A | K43: =VLOOKUP(Table1[[#This Row],[Project Code]],'[6]Combined Nov''25'!$E:$K,6,FALSE) -> #N/A | L43: Ministry of Tourism | M43: Ministry | N43: =VLOOKUP(Table1[[#This Row],[Project Code]],'[6]Combined Nov''25'!$E:$K,7,FALSE) -> #N/A | O43: Financial Mgmt, Policy Analysis & Research | P43: Pan India | Q43: TPI/TPA/TPE/TPQA | T43: =VLOOKUP(Table1[[#This Row],[Project Code]],'[6]Combined Nov''25'!$E:$P,12,FALSE) -> #N/A | U43: #N/A | V43: #N/A | W43: #N/A | X43: No | Y43: No | Z43: No | AA43: No | AB43: No | AC43: No | AD43: No | AE43: No | AF43: No | AG43: No | AH43: No | AI43: No | AJ43: No | AK43: No
A44: 43 | B44: PP00030 | C44: Airport Authority of India | J44: =VLOOKUP(Table1[[#This Row],[Project Code]],'[6]Combined Nov''25'!$E:$O,10,FALSE) -> #N/A | K44: =VLOOKUP(Table1[[#This Row],[Project Code]],'[6]Combined Nov''25'!$E:$K,6,FALSE) -> #N/A | L44: Airports Authority of India | M44: Ministry | N44: =VLOOKUP(Table1[[#This Row],[Project Code]],'[6]Combined Nov''25'!$E:$K,7,FALSE) -> #N/A | O44: Structural & Utilities Management | P44: Pan India | Q44: Capacity building & Impact Assessment | T44: =VLOOKUP(Table1[[#This Row],[Project Code]],'[6]Combined Nov''25'!$E:$P,12,FALSE) -> #N/A | U44: #N/A | V44: #N/A | W44: #N/A | X44: No | Y44: No | Z44: No | AA44: No | AB44: No | AC44: No | AD44: No | AE44: No | AF44: No | AG44: No | AH44: No | AI44: No | AJ44: No | AK44: No
A45: 44 | B45: PP00031 | C45: TPA of ALIMCO Kanpur & APCs | D45: F & H | E45: Ankita Garg | G45: =VLOOKUP(Table1[[#This Row],[Project Code]],[1]Combined!$E:$I,5,FALSE) -> Fully Closed | H45: =VLOOKUP(Table1[[#This Row],[Project Code]],'[2]Combined '!$E:$N,8,FALSE) -> 42879 | K45: =VLOOKUP(Table1[[#This Row],[Project Code]],'[6]Combined Nov''25'!$E:$K,6,FALSE) -> MoSJ | L45: Ministry of Social Justice and Empowerment | M45: Ministry | N45: Social Welfare | O45: Social Welfare, Education & Skill Development | P45: Uttar Pradesh | Q45: TPI/TPA/TPE/TPQA | T45: Conducting Third-Party Assessment of selected products at ALIMCO's HQ and APCs. The annual assessment for ALIMCO's selected products is going on since 2018 wherein third-party assessment is being conducted at Kanpur and five Auxiliary Production Centers (APCs) of ALIMCO - Mohali, Ujjain, Jabalpur, Bhubaneswar and Bengaluru. | U45: The annual assessment for ALIMCO's selected products is going on since 2018 wherein third-party assessment is being conducted at Kanpur and five Auxiliary Production Centers (APCs) of ALIMCO - Mohali, Ujjain, Jabalpur, Bhubaneswar and Bengaluru. Assessments at all six locations of ALIMCO APC has been completed and reports have also been submitted. | V45: Nomination | W45: 4804272 | X45: No | Y45: No | Z45: No | AA45: No | AB45: No | AC45: No | AD45: No | AE45: No | AF45: No | AG45: No | AH45: No | AI45: No | AJ45: No | AK45: No
A46: 45 | B46: PP00032 | C46: UP Healthcare | J46: =VLOOKUP(Table1[[#This Row],[Project Code]],'[6]Combined Nov''25'!$E:$O,10,FALSE) -> #N/A | K46: =VLOOKUP(Table1[[#This Row],[Project Code]],'[6]Combined Nov''25'!$E:$K,6,FALSE) -> #N/A | L46: Government of Uttar Pradesh | M46: State Govt. | N46: =VLOOKUP(Table1[[#This Row],[Project Code]],'[6]Combined Nov''25'!$E:$K,7,FALSE) -> #N/A | O46: Structural & Utilities Management | P46: Uttar Pradesh | Q46: TPI/TPA/TPE/TPQA | T46: =VLOOKUP(Table1[[#This Row],[Project Code]],'[6]Combined Nov''25'!$E:$P,12,FALSE) -> #N/A | U46: #N/A | V46: #N/A | W46: #N/A | X46: No | Y46: No | Z46: Yes | AA46: No | AB46: Yes | AC46: Yes | AD46: No | AE46: No | AF46: No | AG46: No | AH46: No | AI46: No | AJ46: No | AK46: No
A47: 46 | B47: PP00033 | C47: Employee State Corp of India (ESIC) | J47: =VLOOKUP(Table1[[#This Row],[Project Code]],'[6]Combined Nov''25'!$E:$O,10,FALSE) -> #N/A | K47: Employees' State Insurance Corporation (ESIC) | L47: Ministry of Labour and Employement | M47: Ministry | N47: =VLOOKUP(Table1[[#This Row],[Project Code]],'[6]Combined Nov''25'!$E:$K,7,FALSE) -> #N/A | O47: Structural & Utilities Management | P47: Pan India | Q47: TPI/TPA/TPE/TPQA | T47: =VLOOKUP(Table1[[#This Row],[Project Code]],'[6]Combined Nov''25'!$E:$P,12,FALSE) -> #N/A | U47: #N/A | V47: #N/A | W47: #N/A | X47: No | Y47: No | Z47: No | AA47: No | AB47: No | AC47: No | AD47: No | AE47: No | AF47: No | AG47: No | AH47: No | AI47: No | AJ47: No | AK47: No
A48: 47 | B48: PP00034 | C48: Police Crime Victimization | J48: =VLOOKUP(Table1[[#This Row],[Project Code]],'[6]Combined Nov''25'!$E:$O,10,FALSE) -> #N/A | K48: Delhi Police | L48: Government of NCT of Delhi | M48: State Govt. | N48: =VLOOKUP(Table1[[#This Row],[Project Code]],'[6]Combined Nov''25'!$E:$K,7,FALSE) -> #N/A | O48: Governanace, Administration & Digital Infrastructure | P48: NCT of Delhi | Q48: TPI/TPA/TPE/TPQA | T48: =VLOOKUP(Table1[[#This Row],[Project Code]],'[6]Combined Nov''25'!$E:$P,12,FALSE) -> #N/A | U48: #N/A | V48: #N/A | W48: #N/A | X48: Yes | Y48: Yes | Z48: Yes | AA48: No | AB48: Yes | AC48: Yes | AD48: Yes | AE48: No | AF48: No | AG48: No | AH48: No | AI48: No | AJ48: No | AK48: No
A49: 48 | B49: PP00035 | C49: Ranking of Police Station - MHA | J49: =VLOOKUP(Table1[[#This Row],[Project Code]],'[6]Combined Nov''25'!$E:$O,10,FALSE) -> #N/A | K49: =VLOOKUP(Table1[[#This Row],[Project Code]],'[6]Combined Nov''25'!$E:$K,6,FALSE) -> #N/A | L49: Ministry of Home Affairs | M49: Ministry | N49: =VLOOKUP(Table1[[#This Row],[Project Code]],'[6]Combined Nov''25'!$E:$K,7,FALSE) -> #N/A | O49: Governanace, Administration & Digital Infrastructure | P49: Pan India | Q49: TPI/TPA/TPE/TPQA | T49: =VLOOKUP(Table1[[#This Row],[Project Code]],'[6]Combined Nov''25'!$E:$P,12,FALSE) -> #N/A | U49: #N/A | V49: #N/A | W49: #N/A | X49: No | Y49: No | Z49: No | AA49: No | AB49: No | AC49: No | AD49: No | AE49: No | AF49: No | AG49: No | AH49: No | AI49: No | AJ49: No | AK49: No
A50: 49 | B50: PP00036 | C50: NAFED | J50: =VLOOKUP(Table1[[#This Row],[Project Code]],'[6]Combined Nov''25'!$E:$O,10,FALSE) -> #N/A | K50: =VLOOKUP(Table1[[#This Row],[Project Code]],'[6]Combined Nov''25'!$E:$K,6,FALSE) -> #N/A | L50: National Agricultural Cooperative Marketing Federation Of India Limited | M50: Ministry | N50: =VLOOKUP(Table1[[#This Row],[Project Code]],'[6]Combined Nov''25'!$E:$K,7,FALSE) -> #N/A | O50: Agriculture, Food Processing & Supply Chain | P50: Rajasthan | Q50: TPI/TPA/TPE/TPQA | T50: =VLOOKUP(Table1[[#This Row],[Project Code]],'[6]Combined Nov''25'!$E:$P,12,FALSE) -> #N/A | U50: #N/A | V50: #N/A | W50: #N/A | X50: No | Y50: No | Z50: Yes | AA50: No | AB50: No | AC50: Yes | AD50: No | AE50: No | AF50: No | AG50: No | AH50: No | AI50: No | AJ50: No | AK50: No
A51: 50 | B51: PP00037 | C51: Government eMarketplace PMU | D51: PF, P&S | E51: Akanksha Tyagi | G51: Fully Closed | H51: =VLOOKUP(Table1[[#This Row],[Project Code]],'[2]Combined '!$E:$N,8,FALSE) -> 43101 | K51: Government e-Marketplace | L51: Department for Promotion of Industry and Internal Trade | M51: Ministry | N51: Commerce | O51: Financial Mgmt, Policy Analysis & Research | P51: Pan India | Q51: Capacity building & Impact Assessment | T51: The PMU is mandated to perform multiple activities as a knowledge and quality partner to GeM to assure quality in the procurement of goods and services, such as conducting research on global best practices in the relevant domain and assisting in its adaptation by GeM. Additionally, working closely with all the stakeholders in GeM, and is also responsible for all the validations of service providers and vendor assessment exemptions, along with promoting & enhancing quality (by ensuring sanity in the marketplace and compliance checks), building capacities, and developing strategies, including, but not limited to creating a strategic framework for identification and validation of relevant seller/product/service certifications for both goods and services. | U51: After an intensive quality check of service providers, 395003 service providers have been assessed, with 2,71,989 being approved and 1,23,014 being rejected on the basis of invalid compliance certificates and/or project experience details. In addition to that, 65,006 requests have been assessed with 30,450 vendors being exempted while 34,556 were rejected during validation of the vendors registering under the exemption category of vendor assessment (i.e. NSIC, BIS, PSU, Societies/Trust and Recommended by govt. authority) till Dec'23. | V51: 0 | W51: 0 | X51: Yes | Y51: No | Z51: No | AA51: No | AB51: No | AC51: Yes | AD51: No | AE51: No | AF51: No | AG51: No | AH51: No | AI51: No | AJ51: No | AK51: No
A52: 51 | B52: PP00038 | C52: DIPP - Product Analysis | J52: =VLOOKUP(Table1[[#This Row],[Project Code]],'[6]Combined Nov''25'!$E:$O,10,FALSE) -> #N/A | K52: =VLOOKUP(Table1[[#This Row],[Project Code]],'[6]Combined Nov''25'!$E:$K,6,FALSE) -> #N/A | L52: Department for Promotion of Industry and Internal Trade | M52: Ministry | N52: =VLOOKUP(Table1[[#This Row],[Project Code]],'[6]Combined Nov''25'!$E:$K,7,FALSE) -> #N/A | O52: Financial Mgmt, Policy Analysis & Research | P52: Pan India | Q52: TPI/TPA/TPE/TPQA | T52: =VLOOKUP(Table1[[#This Row],[Project Code]],'[6]Combined Nov''25'!$E:$P,12,FALSE) -> #N/A | U52: #N/A | V52: #N/A | W52: #N/A | X52: Yes | Y52: Yes | Z52: Yes | AA52: No | AB52: No | AC52: Yes | AD52: No | AE52: No | AF52: No | AG52: No | AH52: No | AI52: No | AJ52: No | AK52: No
A53: 52 | B53: PP00039 | C53: NCPCR | J53: =VLOOKUP(Table1[[#This Row],[Project Code]],'[6]Combined Nov''25'!$E:$O,10,FALSE) -> #N/A | K53: =VLOOKUP(Table1[[#This Row],[Project Code]],'[6]Combined Nov''25'!$E:$K,6,FALSE) -> #N/A | L53: National Commission for Protection of Child Rights | M53: Ministry | N53: =VLOOKUP(Table1[[#This Row],[Project Code]],'[6]Combined Nov''25'!$E:$K,7,FALSE) -> #N/A | O53: Governanace, Administration & Digital Infrastructure | P53: Pan India | Q53: TPI/TPA/TPE/TPQA | T53: =VLOOKUP(Table1[[#This Row],[Project Code]],'[6]Combined Nov''25'!$E:$P,12,FALSE) -> #N/A | U53: #N/A | V53: #N/A | W53: #N/A | X53: No | Y53: No | Z53: Yes | AA53: No | AB53: No | AC53: Yes | AD53: No | AE53: No | AF53: No | AG53: No | AH53: No | AI53: No | AJ53: No | AK53: No
A54: 53 | B54: PP00040 | C54: EDIFY | J54: =VLOOKUP(Table1[[#This Row],[Project Code]],'[6]Combined Nov''25'!$E:$O,10,FALSE) -> #N/A | K54: =VLOOKUP(Table1[[#This Row],[Project Code]],'[6]Combined Nov''25'!$E:$K,6,FALSE) -> #N/A | L54: The Energy and Resources Institute | M54: University | N54: =VLOOKUP(Table1[[#This Row],[Project Code]],'[6]Combined Nov''25'!$E:$K,7,FALSE) -> #N/A | O54: Financial Mgmt, Policy Analysis & Research | P54: Pan India | Q54: TPI/TPA/TPE/TPQA | T54: =VLOOKUP(Table1[[#This Row],[Project Code]],'[6]Combined Nov''25'!$E:$P,12,FALSE) -> #N/A | U54: #N/A | V54: #N/A | W54: #N/A | X54: No | Y54: No | Z54: No | AA54: No | AB54: No | AC54: No | AD54: No | AE54: No | AF54: No | AG54: No | AH54: No | AI54: No | AJ54: No | AK54: No
A55: 54 | B55: PP00041 | C55: NULM (Hupa Project) | J55: =VLOOKUP(Table1[[#This Row],[Project Code]],'[6]Combined Nov''25'!$E:$O,10,FALSE) -> #N/A | K55: =VLOOKUP(Table1[[#This Row],[Project Code]],'[6]Combined Nov''25'!$E:$K,6,FALSE) -> #N/A | L55: Ministry of Housing and Urban Affairs | M55: Ministry | N55: =VLOOKUP(Table1[[#This Row],[Project Code]],'[6]Combined Nov''25'!$E:$K,7,FALSE) -> #N/A | O55: Structural & Utilities Management | P55: Pan India | Q55: TPI/TPA/TPE/TPQA | T55: =VLOOKUP(Table1[[#This Row],[Project Code]],'[6]Combined Nov''25'!$E:$P,12,FALSE) -> #N/A | U55: #N/A | V55: #N/A | W55: #N/A | X55: Yes | Y55: Yes | Z55: Yes | AA55: No | AB55: Yes | AC55: Yes | AD55: No | AE55: No | AF55: No | AG55: No | AH55: No | AI55: No | AJ55: No | AK55: No
A56: 55 | B56: PP00042 | C56: MHA Project ( MHA & Profiling Project Expense) | J56: =VLOOKUP(Table1[[#This Row],[Project Code]],'[6]Combined Nov''25'!$E:$O,10,FALSE) -> #N/A | K56: Confidential | M56: Ministry | N56: =VLOOKUP(Table1[[#This Row],[Project Code]],'[6]Combined Nov''25'!$E:$K,7,FALSE) -> #N/A | O56: Others | P56: Pan India | Q56: Others | T56: =VLOOKUP(Table1[[#This Row],[Project Code]],'[6]Combined Nov''25'!$E:$P,12,FALSE) -> #N/A | U56: #N/A | V56: #N/A | W56: #N/A | X56: Yes | Y56: No | Z56: Yes | AA56: Yes | AB56: Yes | AC56: Yes | AD56: No | AE56: No | AF56: No | AG56: No | AH56: No | AI56: No | AJ56: No | AK56: No
A57: 56 | B57: PP00043 | C57: RCFL Triveni (RCFL Project Expense) | J57: =VLOOKUP(Table1[[#This Row],[Project Code]],'[6]Combined Nov''25'!$E:$O,10,FALSE) -> #N/A | K57: =VLOOKUP(Table1[[#This Row],[Project Code]],'[6]Combined Nov''25'!$E:$K,6,FALSE) -> #N/A | L57: Ministry of Petroleum and Natural Gas | M57: Ministry | N57: =VLOOKUP(Table1[[#This Row],[Project Code]],'[6]Combined Nov''25'!$E:$K,7,FALSE) -> #N/A | O57: Mining & Metallurgy | P57: Pan India | Q57: TPI/TPA/TPE/TPQA | T57: =VLOOKUP(Table1[[#This Row],[Project Code]],'[6]Combined Nov''25'!$E:$P,12,FALSE) -> #N/A | U57: #N/A | V57: #N/A | W57: #N/A | X57: Yes | Y57: No | Z57: Yes | AA57: Yes | AB57: Yes | AC57: Yes | AD57: No | AE57: No | AF57: No | AG57: No | AH57: No | AI57: No | AJ57: No | AK57: No
A58: 57 | B58: PP00044 | C58: Swachh Ports -2019 | J58: =VLOOKUP(Table1[[#This Row],[Project Code]],'[6]Combined Nov''25'!$E:$O,10,FALSE) -> #N/A | K58: =VLOOKUP(Table1[[#This Row],[Project Code]],'[6]Combined Nov''25'!$E:$K,6,FALSE) -> #N/A | L58: Ministry of Ports, Shipping and Waterways | M58: Ministry | N58: =VLOOKUP(Table1[[#This Row],[Project Code]],'[6]Combined Nov''25'!$E:$K,7,FALSE) -> #N/A | O58: Water & Sanitation | P58: Pan India | Q58: TPI/TPA/TPE/TPQA | T58: =VLOOKUP(Table1[[#This Row],[Project Code]],'[6]Combined Nov''25'!$E:$P,12,FALSE) -> #N/A | U58: #N/A | V58: #N/A | W58: #N/A | X58: No | Y58: No | Z58: No | AA58: No | AB58: No | AC58: No | AD58: No | AE58: No | AF58: No | AG58: No | AH58: No | AI58: No | AJ58: No | AK58: No
A59: 58 | B59: PP00045 | C59: National Smart Grid Mission (NSGM) | J59: =VLOOKUP(Table1[[#This Row],[Project Code]],'[6]Combined Nov''25'!$E:$O,10,FALSE) -> #N/A | K59: =VLOOKUP(Table1[[#This Row],[Project Code]],'[6]Combined Nov''25'!$E:$K,6,FALSE) -> #N/A | L59: Ministry of Power | M59: Ministry | N59: =VLOOKUP(Table1[[#This Row],[Project Code]],'[6]Combined Nov''25'!$E:$K,7,FALSE) -> #N/A | O59: Structural & Utilities Management | P59: Pan India | Q59: TPI/TPA/TPE/TPQA | T59: =VLOOKUP(Table1[[#This Row],[Project Code]],'[6]Combined Nov''25'!$E:$P,12,FALSE) -> #N/A | U59: #N/A | V59: #N/A | W59: #N/A | X59: No | Y59: No | Z59: No | AA59: No | AB59: No | AC59: No | AD59: No | AE59: No | AF59: No | AG59: No | AH59: No | AI59: No | AJ59: No | AK59: No
A60: 59 | B60: PP00046 | C60: National Commission for Scheduled Tribes, Ministry of Tribal Affairs | J60: =VLOOKUP(Table1[[#This Row],[Project Code]],'[6]Combined Nov''25'!$E:$O,10,FALSE) -> #N/A | K60: =VLOOKUP(Table1[[#This Row],[Project Code]],'[6]Combined Nov''25'!$E:$K,6,FALSE) -> #N/A | L60: Ministry of Tribal Affairs | M60: Ministry | N60: =VLOOKUP(Table1[[#This Row],[Project Code]],'[6]Combined Nov''25'!$E:$K,7,FALSE) -> #N/A | O60: Governanace, Administration & Digital Infrastructure | P60: Pan India | Q60: PMU/PMC | T60: =VLOOKUP(Table1[[#This Row],[Project Code]],'[6]Combined Nov''25'!$E:$P,12,FALSE) -> #N/A | U60: #N/A | V60: #N/A | W60: #N/A | X60: No | Y60: No | Z60: No | AA60: No | AB60: No | AC60: No | AD60: No | AE60: No | AF60: No | AG60: No | AH60: No | AI60: No | AJ60: No | AK60: No
A61: 60 | B61: PP00047 | C61: AB PMJAY Quality Certification Scheme | D61: F & H | E61: Ankita Garg | G61: =VLOOKUP(Table1[[#This Row],[Project Code]],[1]Combined!$E:$I,5,FALSE) -> Ongoing | H61: =VLOOKUP(Table1[[#This Row],[Project Code]],'[2]Combined '!$E:$N,8,FALSE) -> 43805 | K61: National Health Authority | L61: Ministry of Health and Family Welfare | M61: Ministry | N61: Health | O61: Governanace, Administration & Digital Infrastructure | P61: Pan India | Q61: TPI/TPA/TPE/TPQA | T61: Partnered with NHA to enhance patient satisfaction and to improve quality standards across the hospitals of the country by bringing a change in healthcare certifications through a unique digital certification initiative called ABPMJAY Quality Certification. Created a three-tier digital certification model (Gold, Silver and Bronze) for Ayushman Bharat with the aim of strengthening the healthcare ecosystem in India | U61: We have created a three-tier digital certification model (Gold, Silver and Bronze) for Ayushman Bharat with the aim of strengthening the healthcare ecosystem in India; and certified 366 hospitals (Gold: 157, Silver: 140, Bronze: 69) | V61: Nomination | W61: 0 | X61: No | Y61: No | Z61: No | AA61: No | AB61: No | AC61: No | AD61: No | AE61: No | AF61: No | AG61: No | AH61: No | AI61: No | AJ61: No | AK61: No
A62: 61 | B62: PP00048 | C62: DIPAM | D62: T,C,W & E | E62: Ashutosh Shringi | G62: =VLOOKUP(Table1[[#This Row],[Project Code]],[1]Combined!$E:$I,5,FALSE) -> Ongoing | H62: =VLOOKUP(Table1[[#This Row],[Project Code]],'[2]Combined '!$E:$N,8,FALSE) -> 43468 | K62: =VLOOKUP(Table1[[#This Row],[Project Code]],'[6]Combined Nov''25'!$E:$K,6,FALSE) -> Ministry of Finance | L62: Ministry of Finance | M62: Ministry | N62: Finance | O62: Financial Mgmt, Policy Analysis & Research | P62: Pan India | Q62: Capacity building & Impact Assessment | T62: Department of Investment and Public Asset Management (DIPAM) deals with all matters relating to management of Central Government investments in equity including disinvestment of equity in Central Public Sector Enterprises(CPSE's). The three major areas of its work relates to Strategic Disinvestment, Minority Stake Sales and Capital Restructuring. All matters relating to sale of Central Government equity through offer for sale or private placement or any other mode as well as strategic disinvestment of CPSE's is dealt with in DIPAM. DIPAM is a Department under the Ministry of Finance. • Project Monitoring: Professionals will have to monitor various transactions being carried out under the supervision of DIPAM. This will involve tracking progress, debottlenecking, stakeholder follow-ups. • Due Diligence: Professionals will have to perform analysis on the feasibility of various ideas from strategic-financial perspective as and when required by DIPAM and produce ready reports for senior officials decision-making. | U62: The key transactions the team was involved in during the last two quarters: 1)OFS - Mazagon Dock (April 2025) , Hindustan Zinc (Nov 2024) 2)Organization of the Leader Communication Workshop for top management of the CPSEs in partnership with CBC on 17th Jan 2025. | V62: Tender | W62: Not fixed | X62: No | Y62: No | Z62: No | AA62: No | AB62: No | AC62: No | AD62: No | AE62: No | AF62: No | AG62: No | AH62: No | AI62: No | AJ62: No | AK62: No
A63: 62 | B63: PP00049 | C63: CPGRAMS | J63: =VLOOKUP(Table1[[#This Row],[Project Code]],'[6]Combined Nov''25'!$E:$O,10,FALSE) -> #N/A | K63: =VLOOKUP(Table1[[#This Row],[Project Code]],'[6]Combined Nov''25'!$E:$K,6,FALSE) -> #N/A | L63: Department of Administrative Reforms and Public Grievances | M63: Ministry | N63: =VLOOKUP(Table1[[#This Row],[Project Code]],'[6]Combined Nov''25'!$E:$K,7,FALSE) -> #N/A | O63: Governanace, Administration & Digital Infrastructure | P63: Pan India | Q63: Capacity building & Impact Assessment | T63: =VLOOKUP(Table1[[#This Row],[Project Code]],'[6]Combined Nov''25'!$E:$P,12,FALSE) -> #N/A | U63: #N/A | V63: #N/A | W63: #N/A | X63: No | Y63: No | Z63: No | AA63: No | AB63: No | AC63: No | AD63: No | AE63: No | AF63: No | AG63: No | AH63: No | AI63: No | AJ63: No | AK63: No
A64: 63 | B64: PP00050 | C64: SVEP project | J64: =VLOOKUP(Table1[[#This Row],[Project Code]],'[6]Combined Nov''25'!$E:$O,10,FALSE) -> #N/A | K64: =VLOOKUP(Table1[[#This Row],[Project Code]],'[6]Combined Nov''25'!$E:$K,6,FALSE) -> #N/A | L64: Ministry of Rural Development | M64: Ministry | N64: =VLOOKUP(Table1[[#This Row],[Project Code]],'[6]Combined Nov''25'!$E:$K,7,FALSE) -> #N/A | O64: Social Welfare, Education & Skill Development | P64: Pan India | Q64: TPI/TPA/TPE/TPQA | T64: =VLOOKUP(Table1[[#This Row],[Project Code]],'[6]Combined Nov''25'!$E:$P,12,FALSE) -> #N/A | U64: #N/A | V64: #N/A | W64: #N/A | X64: No | Y64: No | Z64: No | AA64: No | AB64: No | AC64: No | AD64: No | AE64: No | AF64: No | AG64: No | AH64: No | AI64: No | AJ64: No | AK64: No
A65: 64 | B65: PP00051 | C65: ODF workshop | J65: =VLOOKUP(Table1[[#This Row],[Project Code]],'[6]Combined Nov''25'!$E:$O,10,FALSE) -> #N/A | K65: =VLOOKUP(Table1[[#This Row],[Project Code]],'[6]Combined Nov''25'!$E:$K,6,FALSE) -> #N/A | L65: Government of Kerala, Government of Nagaland, Government of Assam | M65: State Govt. | N65: =VLOOKUP(Table1[[#This Row],[Project Code]],'[6]Combined Nov''25'!$E:$K,7,FALSE) -> #N/A | O65: Water & Sanitation | P65: Kerala, Nagaland, Assam | Q65: Capacity building & Impact Assessment | T65: =VLOOKUP(Table1[[#This Row],[Project Code]],'[6]Combined Nov''25'!$E:$P,12,FALSE) -> #N/A | U65: #N/A | V65: #N/A | W65: #N/A | X65: No | Y65: No | Z65: No | AA65: No | AB65: No | AC65: No | AD65: No | AE65: No | AF65: No | AG65: No | AH65: No | AI65: No | AJ65: No | AK65: No
A66: 65 | B66: PP00052 | C66: TPT of Fisheries for Formaldehyde, Govt of Goa- Fish | D66: NR | E66: Kuwar Ashish | G66: =VLOOKUP(Table1[[#This Row],[Project Code]],[1]Combined!$E:$I,5,FALSE) -> Ongoing | H66: =VLOOKUP(Table1[[#This Row],[Project Code]],'[2]Combined '!$E:$N,8,FALSE) -> 43631 | K66: Food and Drugs Authority | L66: Government of Goa | M66: State Govt. | N66: Fishery | O66: Agriculture, Food Processing & Supply Chain | P66: Goa | Q66: TPI/TPA/TPE/TPQA | T66: FDA Goa has nominated QCI for Third-Party Testing of Fisheries to check the presence of added Formaldehyde. The samples are collected and tested for the presence of formaldehyde in fish and fishery products being consumed in Goa. QCI is checking each of the vehicles carrying fish entering Goa’s for two of it’s major state borders (Patradevi & Polem) and in Margao wholesale fish market. The objective is to provide unadulterated fish for a healthy life to each individual in state of Goa. | U66: A total of 348813 fish carrying vehicles screened since inception | V66: Nomination | W66: 0 | X66: No | Y66: No | Z66: No | AA66: No | AB66: No | AC66: No | AD66: No | AE66: No | AF66: No | AG66: No | AH66: No | AI66: No | AJ66: No | AK66: No
A67: 66 | B67: PP00053 | C67: Qualitative and Quantitative Analysis of Coal Supplied to SEMBCORP Energy India Limited (SEMBCORP) | J67: =VLOOKUP(Table1[[#This Row],[Project Code]],'[6]Combined Nov''25'!$E:$O,10,FALSE) -> #N/A | K67: SEMBCORP | M67: Corporate | N67: =VLOOKUP(Table1[[#This Row],[Project Code]],'[6]Combined Nov''25'!$E:$K,7,FALSE) -> #N/A | O67: Mining & Metallurgy | P67: Pan India | Q67: TPI/TPA/TPE/TPQA | T67: =VLOOKUP(Table1[[#This Row],[Project Code]],'[6]Combined Nov''25'!$E:$P,12,FALSE) -> #N/A | U67: #N/A | V67: #N/A | W67: #N/A | X67: No | Y67: No | Z67: No | AA67: No | AB67: No | AC67: No | AD67: No | AE67: No | AF67: No | AG67: No | AH67: No | AI67: No | AJ67: No | AK67: No
A68: 67 | B68: PP00054 | C68: Analysis & Research Unit | J68: =VLOOKUP(Table1[[#This Row],[Project Code]],'[6]Combined Nov''25'!$E:$O,10,FALSE) -> #N/A | K68: Confidential | M68: Ministry | N68: =VLOOKUP(Table1[[#This Row],[Project Code]],'[6]Combined Nov''25'!$E:$K,7,FALSE) -> #N/A | O68: Others | P68: Pan India | Q68: Others | T68: =VLOOKUP(Table1[[#This Row],[Project Code]],'[6]Combined Nov''25'!$E:$P,12,FALSE) -> #N/A | U68: #N/A | V68: #N/A | W68: #N/A | X68: No | Y68: No | Z68: No | AA68: No | AB68: No | AC68: No | AD68: No | AE68: No | AF68: No | AG68: No | AH68: No | AI68: No | AJ68: No | AK68: No
A69: 68 | B69: PP00055 | C69: GeM Vendor Assessment | D69: PF, P&S | E69: Aashna Arora | G69: =VLOOKUP(Table1[[#This Row],[Project Code]],[1]Combined!$E:$I,5,FALSE) -> Completed | H69: =VLOOKUP(Table1[[#This Row],[Project Code]],'[2]Combined '!$E:$N,8,FALSE) -> 43626 | K69: Government e-Marketplace | L69: Department for Promotion of Industry and Internal Trade | M69: Ministry | N69: Commerce | O69: Financial Mgmt, Policy Analysis & Research | P69: Pan India | Q69: TPI/TPA/TPE/TPQA | T69: The Vendor Validation process is a mechanism for evaluation of vendors and their performance on various predefined parameters. It aims to recognize and bring out reliable vendors that consistently meet or exceed the expectations and requirements of the buyers. The primary objective of the project is to validate and authenticate vendors registering on the GeM portal, resulting in the elimination of deceitful vendors, compromising the quality of the products & services. Furthermore, considering that all the products and services on the GeM portal are intended for government entities, it helps the buyers procure goods and services from reliable vendors offering high-quality products and services, thereby enhancing procurement efficiency, and reducing the risk of substandard products and services. | U69: A total of 18,165 OEM assessment applications including domestic and international assessments covering countries like the USA, Canada, Singapore, Malaysia, and Japan, among many others and 1,877 Reseller applications have been completed and project closure is being discussed at the client end. | V69: 0 | W69: 0 | X69: No | Y69: Yes | Z69: No | AA69: No | AB69: No | AC69: No | AD69: No | AE69: No | AF69: No | AG69: No | AH69: No | AI69: No | AJ69: No | AK69: No
A70: 69 | B70: PP00056 | C70: Kayakalp project | J70: =VLOOKUP(Table1[[#This Row],[Project Code]],'[6]Combined Nov''25'!$E:$O,10,FALSE) -> #N/A | K70: =VLOOKUP(Table1[[#This Row],[Project Code]],'[6]Combined Nov''25'!$E:$K,6,FALSE) -> #N/A | L70: Ministry of Health and Family Welfare | M70: Ministry | N70: =VLOOKUP(Table1[[#This Row],[Project Code]],'[6]Combined Nov''25'!$E:$K,7,FALSE) -> #N/A | O70: Governanace, Administration & Digital Infrastructure | P70: Pan India | Q70: TPI/TPA/TPE/TPQA | T70: =VLOOKUP(Table1[[#This Row],[Project Code]],'[6]Combined Nov''25'!$E:$P,12,FALSE) -> #N/A | U70: #N/A | V70: #N/A | W70: #N/A | X70: No | Y70: No | Z70: No | AA70: No | AB70: No | AC70: No | AD70: No | AE70: No | AF70: No | AG70: No | AH70: No | AI70: No | AJ70: No | AK70: No
A71: 70 | B71: PP00057 | C71: Atal Innovation Mission | J71: =VLOOKUP(Table1[[#This Row],[Project Code]],'[6]Combined Nov''25'!$E:$O,10,FALSE) -> #N/A | K71: =VLOOKUP(Table1[[#This Row],[Project Code]],'[6]Combined Nov''25'!$E:$K,6,FALSE) -> #N/A | L71: NITI Aayog | M71: Ministry | N71: =VLOOKUP(Table1[[#This Row],[Project Code]],'[6]Combined Nov''25'!$E:$K,7,FALSE) -> #N/A | O71: Social Welfare, Education & Skill Development | P71: Pan India | Q71: TPI/TPA/TPE/TPQA | T71: =VLOOKUP(Table1[[#This Row],[Project Code]],'[6]Combined Nov''25'!$E:$P,12,FALSE) -> #N/A | U71: #N/A | V71: #N/A | W71: #N/A | X71: No | Y71: No | Z71: No | AA71: No | AB71: No | AC71: No | AD71: No | AE71: No | AF71: No | AG71: No | AH71: No | AI71: No | AJ71: No | AK71: No
A72: 71 | B72: PP00058 | C72: Swachh Rail-2019 | J72: =VLOOKUP(Table1[[#This Row],[Project Code]],'[6]Combined Nov''25'!$E:$O,10,FALSE) -> #N/A | K72: =VLOOKUP(Table1[[#This Row],[Project Code]],'[6]Combined Nov''25'!$E:$K,6,FALSE) -> #N/A | L72: Ministry of Railways | M72: Ministry | N72: =VLOOKUP(Table1[[#This Row],[Project Code]],'[6]Combined Nov''25'!$E:$K,7,FALSE) -> #N/A | O72: Water & Sanitation | P72: Pan India | Q72: TPI/TPA/TPE/TPQA | T72: =VLOOKUP(Table1[[#This Row],[Project Code]],'[6]Combined Nov''25'!$E:$P,12,FALSE) -> #N/A | U72: #N/A | V72: #N/A | W72: #N/A | X72: No | Y72: No | Z72: No | AA72: No | AB72: No | AC72: No | AD72: No | AE72: No | AF72: No | AG72: No | AH72: No | AI72: No | AJ72: No | AK72: No
A73: 72 | B73: PP00059 | C73: MoRTH - Awards 2019 | J73: =VLOOKUP(Table1[[#This Row],[Project Code]],'[6]Combined Nov''25'!$E:$O,10,FALSE) -> #N/A | K73: =VLOOKUP(Table1[[#This Row],[Project Code]],'[6]Combined Nov''25'!$E:$K,6,FALSE) -> #N/A | L73: Ministry of Road Transport and Highways | M73: Ministry | N73: =VLOOKUP(Table1[[#This Row],[Project Code]],'[6]Combined Nov''25'!$E:$K,7,FALSE) -> #N/A | O73: Governanace, Administration & Digital Infrastructure | P73: Pan India | Q73: Capacity building & Impact Assessment | T73: =VLOOKUP(Table1[[#This Row],[Project Code]],'[6]Combined Nov''25'!$E:$P,12,FALSE) -> #N/A | U73: #N/A | V73: #N/A | W73: #N/A | X73: No | Y73: No | Z73: No | AA73: No | AB73: No | AC73: No | AD73: No | AE73: No | AF73: No | AG73: No | AH73: No | AI73: No | AJ73: No | AK73: No
A74: 73 | B74: PP00060 | C74: Swachh UP(LOBs) | J74: =VLOOKUP(Table1[[#This Row],[Project Code]],'[6]Combined Nov''25'!$E:$O,10,FALSE) -> #N/A | K74: =VLOOKUP(Table1[[#This Row],[Project Code]],'[6]Combined Nov''25'!$E:$K,6,FALSE) -> #N/A | L74: Government of Uttar Pradesh | M74: State Govt. | N74: =VLOOKUP(Table1[[#This Row],[Project Code]],'[6]Combined Nov''25'!$E:$K,7,FALSE) -> #N/A | O74: Water & Sanitation | P74: Uttar Pradesh | Q74: TPI/TPA/TPE/TPQA | T74: =VLOOKUP(Table1[[#This Row],[Project Code]],'[6]Combined Nov''25'!$E:$P,12,FALSE) -> #N/A | U74: #N/A | V74: #N/A | W74: #N/A | X74: No | Y74: No | Z74: No | AA74: No | AB74: No | AC74: No | AD74: No | AE74: No | AF74: No | AG74: No | AH74: No | AI74: No | AJ74: No | AK74: No
A75: 74 | B75: PP00061 | C75: Maharashtra toilet survey | J75: =VLOOKUP(Table1[[#This Row],[Project Code]],'[6]Combined Nov''25'!$E:$O,10,FALSE) -> #N/A | K75: =VLOOKUP(Table1[[#This Row],[Project Code]],'[6]Combined Nov''25'!$E:$K,6,FALSE) -> #N/A | L75: Government of Maharashtra | M75: State Govt. | N75: =VLOOKUP(Table1[[#This Row],[Project Code]],'[6]Combined Nov''25'!$E:$K,7,FALSE) -> #N/A | O75: Water & Sanitation | P75: Maharashtra | Q75: TPI/TPA/TPE/TPQA | T75: =VLOOKUP(Table1[[#This Row],[Project Code]],'[6]Combined Nov''25'!$E:$P,12,FALSE) -> #N/A | U75: #N/A | V75: #N/A | W75: #N/A | X75: No | Y75: No | Z75: No | AA75: No | AB75: No | AC75: No | AD75: No | AE75: No | AF75: No | AG75: No | AH75: No | AI75: No | AJ75: No | AK75: No
A76: 75 | B76: PP00062 | C76: SWM Haryana Project | J76: =VLOOKUP(Table1[[#This Row],[Project Code]],'[6]Combined Nov''25'!$E:$O,10,FALSE) -> #N/A | K76: =VLOOKUP(Table1[[#This Row],[Project Code]],'[6]Combined Nov''25'!$E:$K,6,FALSE) -> #N/A | L76: Government of Haryana | M76: State Govt. | N76: =VLOOKUP(Table1[[#This Row],[Project Code]],'[6]Combined Nov''25'!$E:$K,7,FALSE) -> #N/A | O76: Water & Sanitation | P76: Haryana | Q76: TPI/TPA/TPE/TPQA | T76: =VLOOKUP(Table1[[#This Row],[Project Code]],'[6]Combined Nov''25'!$E:$P,12,FALSE) -> #N/A | U76: #N/A | V76: #N/A | W76: #N/A | X76: No | Y76: No | Z76: No | AA76: No | AB76: No | AC76: No | AD76: No | AE76: No | AF76: No | AG76: No | AH76: No | AI76: No | AJ76: No | AK76: No
A77: 76 | B77: PP00063 | C77: MHA Profiling Project 2019 | J77: =VLOOKUP(Table1[[#This Row],[Project Code]],'[6]Combined Nov''25'!$E:$O,10,FALSE) -> #N/A | K77: Confidential | M77: Ministry | N77: =VLOOKUP(Table1[[#This Row],[Project Code]],'[6]Combined Nov''25'!$E:$K,7,FALSE) -> #N/A | O77: Others | P77: Pan India | Q77: Others | T77: =VLOOKUP(Table1[[#This Row],[Project Code]],'[6]Combined Nov''25'!$E:$P,12,FALSE) -> #N/A | U77: #N/A | V77: #N/A | W77: #N/A | X77: No | Y77: No | Z77: No | AA77: No | AB77: No | AC77: No | AD77: No | AE77: No | AF77: No | AG77: No | AH77: No | AI77: No | AJ77: No | AK77: No
A78: 77 | B78: PP00064 | C78: CAG Project | J78: =VLOOKUP(Table1[[#This Row],[Project Code]],'[6]Combined Nov''25'!$E:$O,10,FALSE) -> #N/A | K78: Comptrollor and Auditor General of India | M78: Ministry | N78: =VLOOKUP(Table1[[#This Row],[Project Code]],'[6]Combined Nov''25'!$E:$K,7,FALSE) -> #N/A | O78: Financial Mgmt, Policy Analysis & Research | P78: Pan India | Q78: PMU/PMC | T78: =VLOOKUP(Table1[[#This Row],[Project Code]],'[6]Combined Nov''25'!$E:$P,12,FALSE) -> #N/A | U78: #N/A | V78: #N/A | W78: #N/A | X78: No | Y78: No | Z78: No | AA78: No | AB78: No | AC78: No | AD78: No | AE78: No | AF78: No | AG78: No | AH78: No | AI78: No | AJ78: No | AK78: No
A79: 78 | B79: PP00065 | C79: Toy Testing Project | J79: =VLOOKUP(Table1[[#This Row],[Project Code]],'[6]Combined Nov''25'!$E:$O,10,FALSE) -> #N/A | K79: =VLOOKUP(Table1[[#This Row],[Project Code]],'[6]Combined Nov''25'!$E:$K,6,FALSE) -> #N/A | L79: Department for Promotion of Industry and Internal Trade | M79: Ministry | N79: =VLOOKUP(Table1[[#This Row],[Project Code]],'[6]Combined Nov''25'!$E:$K,7,FALSE) -> #N/A | O79: Others | P79: Pan India | Q79: TPI/TPA/TPE/TPQA | T79: =VLOOKUP(Table1[[#This Row],[Project Code]],'[6]Combined Nov''25'!$E:$P,12,FALSE) -> #N/A | U79: #N/A | V79: #N/A | W79: #N/A | X79: No | Y79: No | Z79: No | AA79: No | AB79: No | AC79: No | AD79: No | AE79: No | AF79: No | AG79: No | AH79: No | AI79: No | AJ79: No | AK79: No
A80: 79 | B80: PP00066 | C80: Economic Survey 2019-2020 Chapter | J80: =VLOOKUP(Table1[[#This Row],[Project Code]],'[6]Combined Nov''25'!$E:$O,10,FALSE) -> #N/A | K80: =VLOOKUP(Table1[[#This Row],[Project Code]],'[6]Combined Nov''25'!$E:$K,6,FALSE) -> #N/A | L80: Ministry of Finance | M80: Ministry | N80: =VLOOKUP(Table1[[#This Row],[Project Code]],'[6]Combined Nov''25'!$E:$K,7,FALSE) -> #N/A | O80: Financial Mgmt, Policy Analysis & Research | P80: Pan India | Q80: Capacity building & Impact Assessment | T80: =VLOOKUP(Table1[[#This Row],[Project Code]],'[6]Combined Nov''25'!$E:$P,12,FALSE) -> #N/A | U80: #N/A | V80: #N/A | W80: #N/A | X80: No | Y80: No | Z80: No | AA80: No | AB80: No | AC80: No | AD80: No | AE80: No | AF80: No | AG80: No | AH80: No | AI80: No | AJ80: No | AK80: No
A81: 80 | B81: PP00067 | C81: National Program/ Project Management Policy Framework (NPMPF) | J81: =VLOOKUP(Table1[[#This Row],[Project Code]],'[6]Combined Nov''25'!$E:$O,10,FALSE) -> #N/A | K81: =VLOOKUP(Table1[[#This Row],[Project Code]],'[6]Combined Nov''25'!$E:$K,6,FALSE) -> #N/A | L81: NITI Aayog | M81: Ministry | N81: =VLOOKUP(Table1[[#This Row],[Project Code]],'[6]Combined Nov''25'!$E:$K,7,FALSE) -> #N/A | O81: Financial Mgmt, Policy Analysis & Research | P81: Pan India | Q81: Capacity building & Impact Assessment | T81: =VLOOKUP(Table1[[#This Row],[Project Code]],'[6]Combined Nov''25'!$E:$P,12,FALSE) -> #N/A | U81: #N/A | V81: #N/A | W81: #N/A | X81: No | Y81: No | Z81: No | AA81: No | AB81: No | AC81: No | AD81: No | AE81: No | AF81: No | AG81: No | AH81: No | AI81: No | AJ81: No | AK81: No
A82: 81 | B82: PP00068 | C82: Design Innovation Centres | J82: =VLOOKUP(Table1[[#This Row],[Project Code]],'[6]Combined Nov''25'!$E:$O,10,FALSE) -> #N/A | K82: =VLOOKUP(Table1[[#This Row],[Project Code]],'[6]Combined Nov''25'!$E:$K,6,FALSE) -> #N/A | L82: Ministry of Human Resource Development | M82: Ministry | N82: =VLOOKUP(Table1[[#This Row],[Project Code]],'[6]Combined Nov''25'!$E:$K,7,FALSE) -> #N/A | O82: Social Welfare, Education & Skill Development | P82: Pan India | Q82: TPI/TPA/TPE/TPQA | T82: =VLOOKUP(Table1[[#This Row],[Project Code]],'[6]Combined Nov''25'!$E:$P,12,FALSE) -> #N/A | U82: #N/A | V82: #N/A | W82: #N/A | X82: No | Y82: No | Z82: No | AA82: No | AB82: No | AC82: No | AD82: No | AE82: No | AF82: No | AG82: No | AH82: No | AI82: No | AJ82: No | AK82: No
A83: 82 | B83: PP00069 | C83: Third party Interim Evaluation of TEQIP Phase 3 | J83: =VLOOKUP(Table1[[#This Row],[Project Code]],'[6]Combined Nov''25'!$E:$O,10,FALSE) -> #N/A | K83: =VLOOKUP(Table1[[#This Row],[Project Code]],'[6]Combined Nov''25'!$E:$K,6,FALSE) -> #N/A | L83: Ministry of Human Resource Development | M83: Ministry | N83: =VLOOKUP(Table1[[#This Row],[Project Code]],'[6]Combined Nov''25'!$E:$K,7,FALSE) -> #N/A | O83: Structural & Utilities Management | P83: Pan India | Q83: TPI/TPA/TPE/TPQA | T83: =VLOOKUP(Table1[[#This Row],[Project Code]],'[6]Combined Nov''25'!$E:$P,12,FALSE) -> #N/A | U83: #N/A | V83: #N/A | W83: #N/A | X83: No | Y83: Yes | Z83: No | AA83: No | AB83: No | AC83: No | AD83: No | AE83: No | AF83: No | AG83: No | AH83: No | AI83: No | AJ83: No | AK83: No
A84: 83 | B84: PP00070 | C84: Lanco Anpara Power Limited - Unloading End Project- Lanco Anpara | D84: NR | E84: Abhishek Mazumdar | G84: Fully Closed | H84: =VLOOKUP(Table1[[#This Row],[Project Code]],'[2]Combined '!$E:$N,8,FALSE) -> 43854 | K84: =VLOOKUP(Table1[[#This Row],[Project Code]],'[6]Combined Nov''25'!$E:$K,6,FALSE) -> LAPL | L84: LAPL | M84: Corporate | N84: Coal | O84: Mining & Metallurgy | P84: Uttar Pradesh | Q84: TPI/TPA/TPE/TPQA | T84: Qualitative analysis of coal at mil bunker of Lanco Anpara Power Limited | U84: A total volume of 16.00 Million Metric Tonnes of Coal has been sampled since the inception. | V84: Nomination | W84: 0 | X84: No | Y84: No | Z84: No | AA84: No | AB84: No | AC84: No | AD84: No | AE84: No | AF84: No | AG84: No | AH84: No | AI84: No | AJ84: No | AK84: No
A85: 84 | B85: PP00071 | C85: Swachhta Excellence Award 2019-20 | J85: =VLOOKUP(Table1[[#This Row],[Project Code]],'[6]Combined Nov''25'!$E:$O,10,FALSE) -> #N/A | K85: =VLOOKUP(Table1[[#This Row],[Project Code]],'[6]Combined Nov''25'!$E:$K,6,FALSE) -> #N/A | L85: Ministry of Housing and Urban Affairs | M85: Ministry | N85: =VLOOKUP(Table1[[#This Row],[Project Code]],'[6]Combined Nov''25'!$E:$K,7,FALSE) -> #N/A | O85: Water & Sanitation | P85: Pan India | Q85: Capacity building & Impact Assessment | T85: =VLOOKUP(Table1[[#This Row],[Project Code]],'[6]Combined Nov''25'!$E:$P,12,FALSE) -> #N/A | U85: #N/A | V85: #N/A | W85: #N/A | X85: No | Y85: Yes | Z85: No | AA85: No | AB85: No | AC85: No | AD85: No | AE85: No | AF85: No | AG85: No | AH85: No | AI85: No | AJ85: No | AK85: No
A86: 85 | B86: PP00072 | C86: SUSV (Support to Urban Street Vendors ) Excellence Award 2019-20 | J86: =VLOOKUP(Table1[[#This Row],[Project Code]],'[6]Combined Nov''25'!$E:$O,10,FALSE) -> #N/A | K86: =VLOOKUP(Table1[[#This Row],[Project Code]],'[6]Combined Nov''25'!$E:$K,6,FALSE) -> #N/A | L86: Ministry of Housing and Urban Affairs | M86: Ministry | N86: =VLOOKUP(Table1[[#This Row],[Project Code]],'[6]Combined Nov''25'!$E:$K,7,FALSE) -> #N/A | O86: Governanace, Administration & Digital Infrastructure | P86: Pan India | Q86: Capacity building & Impact Assessment | T86: =VLOOKUP(Table1[[#This Row],[Project Code]],'[6]Combined Nov''25'!$E:$P,12,FALSE) -> #N/A | U86: #N/A | V86: #N/A | W86: #N/A | X86: No | Y86: No | Z86: No | AA86: No | AB86: No | AC86: No | AD86: No | AE86: No | AF86: No | AG86: No | AH86: No | AI86: No | AJ86: No | AK86: No
A87: 86 | B87: PP00073 | C87: PMU for Policy Analysis, Research and Data Analytics | D87: Governance | E87: Anoushka Ghonkrokta | G87: =VLOOKUP(Table1[[#This Row],[Project Code]],[1]Combined!$E:$I,5,FALSE) -> Ongoing | H87: =VLOOKUP(Table1[[#This Row],[Project Code]],'[2]Combined '!$E:$N,8,FALSE) -> 43739 | J87: =VLOOKUP(Table1[[#This Row],[Project Code]],'[6]Combined Nov''25'!$E:$O,10,FALSE) -> 46721 | K87: =VLOOKUP(Table1[[#This Row],[Project Code]],'[6]Combined Nov''25'!$E:$K,6,FALSE) -> Ministry of Finance | L87: Ministry of Finance | M87: Ministry | N87: =VLOOKUP(Table1[[#This Row],[Project Code]],'[6]Combined Nov''25'!$E:$K,7,FALSE) -> 0 | O87: Financial Mgmt, Policy Analysis & Research | P87: Pan India | Q87: Capacity building & Impact Assessment | T87: =VLOOKUP(Table1[[#This Row],[Project Code]],'[6]Combined Nov''25'!$E:$P,12,FALSE) -> 0 | U87: 0 | V87: Nomination | W87: 10886400 | X87: No | Y87: No | Z87: No | AA87: No | AB87: No | AC87: No | AD87: No | AE87: No | AF87: No | AG87: No | AH87: No | AI87: No | AJ87: No | AK87: No
A88: 87 | B88: PP00074 | C88: Census Survey of Water Body in ganga Basin | J88: =VLOOKUP(Table1[[#This Row],[Project Code]],'[6]Combined Nov''25'!$E:$O,10,FALSE) -> #N/A | K88: National Mission for Clean Ganga | L88: Ministry of Jal Shakti | M88: Ministry | N88: =VLOOKUP(Table1[[#This Row],[Project Code]],'[6]Combined Nov''25'!$E:$K,7,FALSE) -> #N/A | O88: Water & Sanitation | P88: Pan India | Q88: TPI/TPA/TPE/TPQA | T88: =VLOOKUP(Table1[[#This Row],[Project Code]],'[6]Combined Nov''25'!$E:$P,12,FALSE) -> #N/A | U88: #N/A | V88: #N/A | W88: #N/A | X88: No | Y88: No | Z88: No | AA88: No | AB88: No | AC88: No | AD88: No | AE88: No | AF88: No | AG88: No | AH88: No | AI88: No | AJ88: No | AK88: No
A89: 88 | B89: PP00075/ PB00006 | C89: CIM | J89: =VLOOKUP(Table1[[#This Row],[Project Code]],'[6]Combined Nov''25'!$E:$O,10,FALSE) -> #N/A | K89: =VLOOKUP(Table1[[#This Row],[Project Code]],'[6]Combined Nov''25'!$E:$K,6,FALSE) -> #N/A | M89: 0 | N89: =VLOOKUP(Table1[[#This Row],[Project Code]],'[6]Combined Nov''25'!$E:$K,7,FALSE) -> #N/A | O89: Financial Mgmt, Policy Analysis & Research | P89: Pan India | Q89: Capacity building & Impact Assessment | T89: =VLOOKUP(Table1[[#This Row],[Project Code]],'[6]Combined Nov''25'!$E:$P,12,FALSE) -> #N/A | U89: #N/A | V89: #N/A | W89: #N/A | X89: No | Y89: No | Z89: No | AA89: No | AB89: No | AC89: No | AD89: No | AE89: No | AF89: No | AG89: No | AH89: No | AI89: No | AJ89: No | AK89: No
A90: 89 | B90: PP00076 | C90: MHA CASU | D90: Governance | E90: Vijay Kohli | G90: =VLOOKUP(Table1[[#This Row],[Project Code]],[1]Combined!$E:$I,5,FALSE) -> Ongoing | J90: =VLOOKUP(Table1[[#This Row],[Project Code]],'[6]Combined Nov''25'!$E:$O,10,FALSE) -> 46111 | K90: =VLOOKUP(Table1[[#This Row],[Project Code]],'[6]Combined Nov''25'!$E:$K,6,FALSE) -> MHA | L90: Ministry of Home Affairs | M90: Ministry | N90: =VLOOKUP(Table1[[#This Row],[Project Code]],'[6]Combined Nov''25'!$E:$K,7,FALSE) -> 0 | O90: Financial Mgmt, Policy Analysis & Research | P90: Pan India | Q90: Capacity building & Impact Assessment | T90: =VLOOKUP(Table1[[#This Row],[Project Code]],'[6]Combined Nov''25'!$E:$P,12,FALSE) -> 0 | U90: 0 | V90: Nomination | W90: 4008430 | X90: No | Y90: No | Z90: No | AA90: No | AB90: No | AC90: No | AD90: No | AE90: No | AF90: No | AG90: No | AH90: No | AI90: No | AJ90: No | AK90: No
A91: 90 | B91: PP00077 | C91: PMU-Ministry of Tourism | J91: =VLOOKUP(Table1[[#This Row],[Project Code]],'[6]Combined Nov''25'!$E:$O,10,FALSE) -> #N/A | K91: =VLOOKUP(Table1[[#This Row],[Project Code]],'[6]Combined Nov''25'!$E:$K,6,FALSE) -> #N/A | L91: Ministry of Tourism | M91: Ministry | N91: =VLOOKUP(Table1[[#This Row],[Project Code]],'[6]Combined Nov''25'!$E:$K,7,FALSE) -> #N/A | O91: Arts, Culture & Tourism | P91: Pan India | Q91: PMU/PMC | T91: =VLOOKUP(Table1[[#This Row],[Project Code]],'[6]Combined Nov''25'!$E:$P,12,FALSE) -> #N/A | U91: #N/A | V91: #N/A | W91: #N/A | X91: No | Y91: No | Z91: No | AA91: No | AB91: No | AC91: No | AD91: No | AE91: No | AF91: No | AG91: No | AH91: No | AI91: No | AJ91: No | AK91: No
A92: 91 | B92: PP00078 | C92: Ministerial Policy and Implementation Dashboard | J92: =VLOOKUP(Table1[[#This Row],[Project Code]],'[6]Combined Nov''25'!$E:$O,10,FALSE) -> #N/A | K92: =VLOOKUP(Table1[[#This Row],[Project Code]],'[6]Combined Nov''25'!$E:$K,6,FALSE) -> #N/A | L92: Ministry of Commerce and Industry & Others | M92: Ministry | N92: =VLOOKUP(Table1[[#This Row],[Project Code]],'[6]Combined Nov''25'!$E:$K,7,FALSE) -> #N/A | O92: Governanace, Administration & Digital Infrastructure | P92: Pan India | Q92: Capacity building & Impact Assessment | T92: =VLOOKUP(Table1[[#This Row],[Project Code]],'[6]Combined Nov''25'!$E:$P,12,FALSE) -> #N/A | U92: #N/A | V92: #N/A | W92: #N/A | X92: No | Y92: Yes | Z92: No | AA92: No | AB92: No | AC92: No | AD92: No | AE92: No | AF92: No | AG92: No | AH92: No | AI92: No | AJ92: No | AK92: No
A93: 92 | B93: PP00079 | C93: Quality assessment of Akash system at BDL Ltd | J93: =VLOOKUP(Table1[[#This Row],[Project Code]],'[6]Combined Nov''25'!$E:$O,10,FALSE) -> #N/A | K93: Defence Research and Developmenr Organisation | L93: Ministry of Defence | M93: Ministry | N93: =VLOOKUP(Table1[[#This Row],[Project Code]],'[6]Combined Nov''25'!$E:$K,7,FALSE) -> #N/A | O93: Governanace, Administration & Digital Infrastructure | P93: Pan India | Q93: TPI/TPA/TPE/TPQA | T93: =VLOOKUP(Table1[[#This Row],[Project Code]],'[6]Combined Nov''25'!$E:$P,12,FALSE) -> #N/A | U93: #N/A | V93: #N/A | W93: #N/A | X93: No | Y93: No | Z93: No | AA93: No | AB93: No | AC93: No | AD93: No | AE93: No | AF93: No | AG93: No | AH93: No | AI93: No | AJ93: No | AK93: No
A94: 93 | B94: PP00080 | C94: DGFT Pulse Importer Facility Assessment | J94: =VLOOKUP(Table1[[#This Row],[Project Code]],'[6]Combined Nov''25'!$E:$O,10,FALSE) -> #N/A | K94: Department for Promotion of Industry and Internal Trade & Director General of Foreign Trade | L94: Ministry of Commerce and Industry | M94: Ministry | N94: =VLOOKUP(Table1[[#This Row],[Project Code]],'[6]Combined Nov''25'!$E:$K,7,FALSE) -> #N/A | O94: Structural & Utilities Management | P94: Pan India | Q94: TPI/TPA/TPE/TPQA | T94: =VLOOKUP(Table1[[#This Row],[Project Code]],'[6]Combined Nov''25'!$E:$P,12,FALSE) -> #N/A | U94: #N/A | V94: #N/A | W94: #N/A | X94: No | Y94: No | Z94: No | AA94: No | AB94: No | AC94: No | AD94: No | AE94: No | AF94: No | AG94: No | AH94: No | AI94: No | AJ94: No | AK94: No
A95: 94 | B95: PP00081 | C95: GeM HS Code | J95: =VLOOKUP(Table1[[#This Row],[Project Code]],'[6]Combined Nov''25'!$E:$O,10,FALSE) -> #N/A | K95: =VLOOKUP(Table1[[#This Row],[Project Code]],'[6]Combined Nov''25'!$E:$K,6,FALSE) -> #N/A | L95: Department for Promotion of Industry and Internal Trade | M95: Ministry | N95: =VLOOKUP(Table1[[#This Row],[Project Code]],'[6]Combined Nov''25'!$E:$K,7,FALSE) -> #N/A | O95: Governanace, Administration & Digital Infrastructure | P95: Pan India | Q95: Capacity building & Impact Assessment | T95: =VLOOKUP(Table1[[#This Row],[Project Code]],'[6]Combined Nov''25'!$E:$P,12,FALSE) -> #N/A | U95: #N/A | V95: #N/A | W95: #N/A | X95: No | Y95: No | Z95: No | AA95: No | AB95: No | AC95: No | AD95: No | AE95: No | AF95: No | AG95: No | AH95: No | AI95: No | AJ95: No | AK95: No
A96: 95 | B96: PP00082 | C96: Audit of Railway Terminals | J96: =VLOOKUP(Table1[[#This Row],[Project Code]],'[6]Combined Nov''25'!$E:$O,10,FALSE) -> #N/A | K96: =VLOOKUP(Table1[[#This Row],[Project Code]],'[6]Combined Nov''25'!$E:$K,6,FALSE) -> #N/A | L96: Ministry of Railways | M96: Ministry | N96: =VLOOKUP(Table1[[#This Row],[Project Code]],'[6]Combined Nov''25'!$E:$K,7,FALSE) -> #N/A | O96: Structural & Utilities Management | P96: Pan India | Q96: Capacity building & Impact Assessment | T96: =VLOOKUP(Table1[[#This Row],[Project Code]],'[6]Combined Nov''25'!$E:$P,12,FALSE) -> #N/A | U96: #N/A | V96: #N/A | W96: #N/A | X96: No | Y96: No | Z96: No | AA96: No | AB96: No | AC96: No | AD96: No | AE96: No | AF96: No | AG96: No | AH96: No | AI96: No | AJ96: No | AK96: No
A97: 96 | B97: PP00083 | C97: MoRTH Award-2020 | J97: =VLOOKUP(Table1[[#This Row],[Project Code]],'[6]Combined Nov''25'!$E:$O,10,FALSE) -> #N/A | K97: =VLOOKUP(Table1[[#This Row],[Project Code]],'[6]Combined Nov''25'!$E:$K,6,FALSE) -> #N/A | L97: Ministry of Road Transport and Highways | M97: Ministry | N97: =VLOOKUP(Table1[[#This Row],[Project Code]],'[6]Combined Nov''25'!$E:$K,7,FALSE) -> #N/A | O97: Governanace, Administration & Digital Infrastructure | P97: Pan India | Q97: Capacity building & Impact Assessment | T97: =VLOOKUP(Table1[[#This Row],[Project Code]],'[6]Combined Nov''25'!$E:$P,12,FALSE) -> #N/A | U97: #N/A | V97: #N/A | W97: #N/A | X97: No | Y97: Yes | Z97: No | AA97: No | AB97: No | AC97: No | AD97: No | AE97: No | AF97: No | AG97: No | AH97: No | AI97: No | AJ97: No | AK97: No
A98: 97 | B98: PP00084 | C98: Profiling Project-2020 | J98: =VLOOKUP(Table1[[#This Row],[Project Code]],'[6]Combined Nov''25'!$E:$O,10,FALSE) -> #N/A | K98: Confidential | M98: Ministry | N98: =VLOOKUP(Table1[[#This Row],[Project Code]],'[6]Combined Nov''25'!$E:$K,7,FALSE) -> #N/A | O98: Others | P98: Pan India | Q98: Others | T98: =VLOOKUP(Table1[[#This Row],[Project Code]],'[6]Combined Nov''25'!$E:$P,12,FALSE) -> #N/A | U98: #N/A | V98: #N/A | W98: #N/A | X98: No | Y98: No | Z98: No | AA98: No | AB98: No | AC98: No | AD98: No | AE98: No | AF98: No | AG98: No | AH98: No | AI98: No | AJ98: No | AK98: No
A99: 98 | B99: PP00085 | C99: Swachh NDMC -2020-2021 | J99: =VLOOKUP(Table1[[#This Row],[Project Code]],'[6]Combined Nov''25'!$E:$O,10,FALSE) -> #N/A | K99: New Delhi Municipal Council | L99: Government of NCT of Delhi | M99: State Govt. | N99: =VLOOKUP(Table1[[#This Row],[Project Code]],'[6]Combined Nov''25'!$E:$K,7,FALSE) -> #N/A | O99: Water & Sanitation | P99: NCT of Delhi | Q99: TPI/TPA/TPE/TPQA | T99: =VLOOKUP(Table1[[#This Row],[Project Code]],'[6]Combined Nov''25'!$E:$P,12,FALSE) -> #N/A | U99: #N/A | V99: #N/A | W99: #N/A | X99: No | Y99: No | Z99: No | AA99: No | AB99: No | AC99: No | AD99: No | AE99: No | AF99: No | AG99: No | AH99: No | AI99: No | AJ99: No | AK99: No
A100: 99 | B100: PP00086 | C100: Unnati | J100: =VLOOKUP(Table1[[#This Row],[Project Code]],'[6]Combined Nov''25'!$E:$O,10,FALSE) -> #N/A | K100: =VLOOKUP(Table1[[#This Row],[Project Code]],'[6]Combined Nov''25'!$E:$K,6,FALSE) -> #N/A | L100: NITI Aayog | M100: Ministry | N100: =VLOOKUP(Table1[[#This Row],[Project Code]],'[6]Combined Nov''25'!$E:$K,7,FALSE) -> #N/A | O100: Financial Mgmt, Policy Analysis & Research | P100: Pan India | Q100: Capacity building & Impact Assessment | T100: =VLOOKUP(Table1[[#This Row],[Project Code]],'[6]Combined Nov''25'!$E:$P,12,FALSE) -> #N/A | U100: #N/A | V100: #N/A | W100: #N/A | X100: No | Y100: No | Z100: No | AA100: No | AB100: No | AC100: No | AD100: No | AE100: No | AF100: No | AG100: No | AH100: No | AI100: No | AJ100: No | AK100: No
...

Sheet Sheet1

Sheet Sheet2
A1: Project Name | B1: Project Code | C1: State | D1: Client/Department | E1: Client/Ministry | F1: Client Type | G1: Sector/Domain (2) | H1: Nature of Project
A2: Confidential | B2: PB00001 | C2: Pan India | F2: Ministry | G2: Others | H2: Others
A3: Census of Traders | B3: PB00002 | C3: Pan India | D3: Department for Promotion of Industry and Internal Trade, | E3: Ministry of Commerce and Industry | F3: Ministry | G3: Financial Mgmt, Policy Analysis & Research | H3: Capacity building & Impact Assessment
A4: Confidential | B4: PB00003 | C4: Pan India | F4: Ministry | G4: Others | H4: Others
A5: TPI of buses, depots, workshops & stations of UP | B5: PB00004 | C5: Uttar Pradesh | D5: Uttar Pradesh State Road Transport Corporation (UPSRTC) | E5: Government of Uttar Pradesh | G5: Structural & Utilities Management | H5: TPI/TPA/TPE/TPQA
A6: Sarpanch Samvaad | B6: PB00011 | C6: Pan India | G6: Social Welfare, Education & Skill Development | H6: Capacity building & Impact Assessment
A7: Quality City Initiative (Nashik) | B7: PB00012 | C7: Maharashtra | D7: Nashik Municipal Corporation | E7: Government of Maharashtra | F7: State Govt. | G7: Water & Sanitation | H7: Others
A8: Trade Surveillance- Leather | B8: PB00013 | C8: Pan India | G8: Agriculture, Food Processing & Supply Chain | H8: TPI/TPA/TPE/TPQA
A9: Quality Assessment of Biogas | B9: PB00014 | C9: Gujarat | D9: Banaskantha District Co-op. Milk Producers' Union Ltd. | E9: Cooperative | F9: Cooperative | G9: Mining & Metallurgy | H9: TPI/TPA/TPE/TPQA
A10: Dipstick Assessment for receipt of free grains under PMGKAY | B10: PB00015 | C10: Pan India | E10: Department of Food and Public Distribution | F10: Ministry | G10: Agriculture, Food Processing & Supply Chain | H10: TPI/TPA/TPE/TPQA
A11: TPI of residential building under Rajasthan Housing Board | B11: PB00016 | C11: Rajasthan | G11: Structural & Utilities Management | H11: TPI/TPA/TPE/TPQA
A12: Social Impact Evaluation of the Projects Undertaken by Sasakawa – India Leprosy Foundation | B12: PB00017 | C12: Pan India | E12: Sasakawa-India Leprosy Foundation. | F12: Non-Profit Organisation | G12: Social Welfare, Education & Skill Development | H12: Capacity building & Impact Assessment
A13: Culture_National Library_2024 | B13: PB00018 | C13: Pan India | E13: Ministry of Culture | F13: Ministry | G13: Arts, Culture & Tourism | H13: Capacity building & Impact Assessment
A14: Assessment, Capacity Building & Certification of Shri Somnath Trust | B14: PB00019 | C14: Gujarat | E14: Shri Somnath Trust | F14: Independent Body | G14: Arts, Culture & Tourism | H14: Capacity building & Impact Assessment
A15: Third Party Sampling, Testing and Analysis of Coal | B15: PP00001 | C15: Pan India | E15: Coal India Limited | F15: PSU | G15: Mining & Metallurgy | H15: TPI/TPA/TPE/TPQA
A16: ODF Verification under SBM Urban | B16: PP00002 | C16: Pan India | E16: Ministry of Housing and Urban Affairs | F16: Ministry | G16: Water & Sanitation | H16: TPI/TPA/TPE/TPQA
A17: MoUD Star Rating - Garbage Free Cities | B17: PP00003 | C17: Pan India | E17: Ministry of Housing and Urban Affairs | F17: Ministry | G17: Water & Sanitation | H17: TPI/TPA/TPE/TPQA
A18: TPI of SWM Status of 97 Ganga Towns | B18: PP00004 | C18: Pan India | E18: Ministry of Housing and Urban Affairs | F18: Ministry | G18: Water & Sanitation | H18: TPI/TPA/TPE/TPQA
A19: India Development Foundation of Overseas Indians Assessment | B19: PP00005 | C19: Pan India | D19: IBF-OI | E19: Govt Body (Not for Profit) | F19: Ministry | G19: Financial Mgmt, Policy Analysis & Research | H19: TPI/TPA/TPE/TPQA
A20: Swachh Survekshan in HPCL Retail Outlets | B20: PP00006 | C20: Pan India | E20: HPCL | F20: PSU | G20: Water & Sanitation | H20: TPI/TPA/TPE/TPQA
A21: Assisting & Capacity Building of 51 ULB's of Madhya Pradesh for Swachh Survekshan 2019 | B21: PP00007 | C21: Madhya Pradesh | E21: Government of Madhya Pradesh | F21: State Govt. | G21: Water & Sanitation | H21: Capacity building & Impact Assessment
A22: Capacity Building at Gwalior Municipal Corporation for Swachh Survekshan 2019 | B22: PP00008 | C22: Madhya Pradesh | D22: Municipal Corporation of Gwalior | E22: Government of Madhya Pradesh | F22: State Govt. | G22: Water & Sanitation | H22: Capacity building & Impact Assessment
A23: Swachh Pradesh Swastha Pradesh, MP -SBM Urban | B23: PP00009 | C23: Madhya Pradesh | E23: Government of Madhya Pradesh | F23: State Govt. | G23: Water & Sanitation | H23: TPI/TPA/TPE/TPQA
A24: Independant Cleanliness of Public Toilets in Delhi | B24: PP00010 | C24: NCT of Delhi | E24: Ministry of Housing and Urban Affairs | F24: Ministry | G24: Water & Sanitation | H24: TPI/TPA/TPE/TPQA
A25: Google Toilet Mapping- SBM Urban | B25: PP00011 | C25: Pan India | E25: Ministry of Housing and Urban Affairs | F25: Ministry | G25: Water & Sanitation | H25: TPI/TPA/TPE/TPQA
A26: Third Party Verification Agency for District Level Verified ODF Gram Panchayats under SBM | B26: PP00012 | C26: Jharkhand | E26: Government of Jharkhand | F26: State Govt. | G26: Water & Sanitation | H26: TPI/TPA/TPE/TPQA
A27: TPA of Railway Stations, Ministry of Railways | B27: PP00013 | C27: Pan India | E27: Ministry of Railways | F27: Ministry | G27: Water & Sanitation | H27: TPI/TPA/TPE/TPQA
A28: Swachh Survekshan Telangana | B28: PP00014 | C28: Telangana | E28: Government of Telangana | F28: State Govt. | G28: Water & Sanitation | H28: TPI/TPA/TPE/TPQA
A29: TPA for High-End Cleaning Assessment at Gujarat Yatradhams | B29: PP00015 | C29: Gujarat | D29: Tourism Corporation of Gujarat Limited | E29: Government of Gujarat | F29: State Govt. | G29: Water & Sanitation | H29: TPI/TPA/TPE/TPQA
A30: TPI of Cleanliness Project by TCGL | B30: PP00016 | C30: Gujarat | D30: Tourism Corporation of Gujarat Limited | E30: Government of Gujarat | F30: State Govt. | G30: Water & Sanitation | H30: TPI/TPA/TPE/TPQA
A31: TPA for High-End Cleaning at Statue of Unity, TCGL | B31: PP00017 | C31: Gujarat | D31: Tourism Corporation of Gujarat Limited | E31: Government of Gujarat | F31: State Govt. | G31: Structural & Utilities Management | H31: TPI/TPA/TPE/TPQA
A32: TPV of ODF Villages under SBM Rural, PRD, Govt of UP | B32: PP00018 | C32: Uttar Pradesh | D32: Department of Panchayati Raj | E32: Government of Uttar Pradesh | F32: State Govt. | G32: Water & Sanitation | H32: TPI/TPA/TPE/TPQA
A33: Assessment of NDMC Preparedness for SS 2019 | B33: PP00019 | C33: NCT of Delhi | D33: New Delhi Municipal Council | E33: Government of NCT of Delhi | F33: State Govt. | G33: Water & Sanitation | H33: TPI/TPA/TPE/TPQA
A34: ALF Swachhta Awards 2019, DAY NULM | B34: PP00020 | C34: Pan India | E34: Ministry of Housing and Urban Affairs | F34: Ministry | G34: Governanace, Administration & Digital Infrastructure | H34: Capacity building & Impact Assessment
A35: Quality Assessment of RAPDRP | B35: PP00021 | C35: Pan India | E35: Ministry of Power | F35: Ministry | G35: Structural & Utilities Management | H35: TPI/TPA/TPE/TPQA
A36: Quality Assessment of Rural Electrification under DDUGKY | B36: PP00022 | C36: Pan India | E36: Ministry of Power | F36: Ministry | G36: Structural & Utilities Management | H36: TPI/TPA/TPE/TPQA
A37: MoPNG - PMU | B37: PP00023 | C37: Pan India | E37: Ministry of Petroleum and Natural Gas | F37: Ministry | G37: Governanace, Administration & Digital Infrastructure | H37: PMU/PMC
A38: Citizen's Charter Enhancement, Department of Administrative Reforms and Public Grievances | B38: PP00024 | C38: Pan India | E38: Department of Administrative Reforms and Public Grievances | F38: Ministry | G38: Governanace, Administration & Digital Infrastructure | H38: Capacity building & Impact Assessment
A39: EOffice Implementation PMU, Department of Administrative Reforms and Public Grievances | B39: PP00025 | C39: Pan India | E39: Department of Administrative Reforms and Public Grievances | F39: Ministry | G39: Governanace, Administration & Digital Infrastructure | H39: PMU/PMC
A40: Department of Administrative Reforms and Public Grievances Dashboard | B40: PP00026 | C40: Pan India | E40: Department of Administrative Reforms and Public Grievances | F40: Ministry | G40: Governanace, Administration & Digital Infrastructure | H40: Capacity building & Impact Assessment
A41: MoRTH- Highway Rating | B41: PP00027 | C41: Pan India | E41: Ministry of Road Transport and Highways | F41: Ministry | G41: Governanace, Administration & Digital Infrastructure | H41: TPI/TPA/TPE/TPQA
A42: MoRTH - Awards 2018 | B42: PP00028 | C42: Pan India | E42: Ministry of Road Transport and Highways | F42: Ministry | G42: Governanace, Administration & Digital Infrastructure | H42: Capacity building & Impact Assessment
A43: Tourism Study - TTCI Index | B43: PP00029 | C43: Pan India | E43: Ministry of Tourism | F43: Ministry | G43: Financial Mgmt, Policy Analysis & Research | H43: TPI/TPA/TPE/TPQA
A44: Capacity Building & TPA of Airports, AAI | B44: PP00030 | C44: Pan India | E44: Airports Authority of India | F44: Ministry | G44: Structural & Utilities Management | H44: Capacity building & Impact Assessment
A45: TPA of ALIMCO Kanpur & APCs | B45: PP00031 | C45: Uttar Pradesh | E45: Ministry of Social Justice and Empowerment | F45: Ministry | G45: Social Welfare, Education & Skill Development | H45: TPI/TPA/TPE/TPQA
A46: TPA of Support Services at Medical Colleges, DGME Govt of UP | B46: PP00032 | C46: Uttar Pradesh | E46: Government of Uttar Pradesh | F46: State Govt. | G46: Structural & Utilities Management | H46: TPI/TPA/TPE/TPQA
A47: TPA & Acrreditation of ESIC Hospitals & Dispensaries | B47: PP00033 | C47: Pan India | D47: Employees' State Insurance Corporation (ESIC) | E47: Ministry of Labour and Employement | F47: Ministry | G47: Structural & Utilities Management | H47: TPI/TPA/TPE/TPQA
A48: Crime Victimization Survey for Delhi Police | B48: PP00034 | C48: NCT of Delhi | D48: Delhi Police | E48: Government of NCT of Delhi | F48: State Govt. | G48: Governanace, Administration & Digital Infrastructure | H48: TPI/TPA/TPE/TPQA
A49: Ranking of Police Station - MHA | B49: PP00035 | C49: Pan India | E49: Ministry of Home Affairs | F49: Ministry | G49: Governanace, Administration & Digital Infrastructure | H49: TPI/TPA/TPE/TPQA
A50: Survey & Analysis of Pulses & Oilseeds under PSS in Rajasthan -NAFED | B50: PP00036 | C50: Rajasthan | E50: National Agricultural Cooperative Marketing Federation Of India Limited | F50: Ministry | G50: Agriculture, Food Processing & Supply Chain | H50: TPI/TPA/TPE/TPQA
A51: Government eMarketplace PMU | B51: PP00037 | C51: Pan India | D51: Government e-Marketplace | E51: Department for Promotion of Industry and Internal Trade | F51: Ministry | G51: Financial Mgmt, Policy Analysis & Research | H51: Capacity building & Impact Assessment
A52: DIPP - Product Analysis (ProBono) | B52: PP00038 | C52: Pan India | E52: Department for Promotion of Industry and Internal Trade | F52: Ministry | G52: Financial Mgmt, Policy Analysis & Research | H52: TPI/TPA/TPE/TPQA
A53: TPA of EWS & DG Ratio in Schools under RTE2009 - NCPCR | B53: PP00039 | C53: Pan India | E53: National Commission for Protection of Child Rights | F53: Ministry | G53: Governanace, Administration & Digital Infrastructure | H53: TPI/TPA/TPE/TPQA
A54: EDIFY | B54: PP00040 | C54: Pan India | E54: The Energy and Resources Institute | F54: University | G54: Financial Mgmt, Policy Analysis & Research | H54: TPI/TPA/TPE/TPQA
A55: TPA of DAY-NULM, Ministry of Housing and Urban Affairs | B55: PP00041 | C55: Pan India | E55: Ministry of Housing and Urban Affairs | F55: Ministry | G55: Structural & Utilities Management | H55: TPI/TPA/TPE/TPQA
A56: Confidential | B56: PP00042 | C56: Pan India | D56: Confidential | F56: Ministry | G56: Others | H56: Others
A57: TPV of Goods Imported by RCFL, Ministry of Chemicals & Fertilizers | B57: PP00043 | C57: Pan India | E57: Ministry of Petroleum and Natural Gas | F57: Ministry | G57: Mining & Metallurgy | H57: TPI/TPA/TPE/TPQA
A58: Indian Ports Association - SBM 2019 | B58: PP00044 | C58: Pan India | E58: Ministry of Ports, Shipping and Waterways | F58: Ministry | G58: Water & Sanitation | H58: TPI/TPA/TPE/TPQA
A59: IA Smart Grid Pilot Project - National Smart Grid Mission | B59: PP00045 | C59: Pan India | E59: Ministry of Power | F59: Ministry | G59: Structural & Utilities Management | H59: TPI/TPA/TPE/TPQA
A60: National Commission for Scheduled Tribes | B60: PP00046 | C60: Pan India | E60: Ministry of Tribal Affairs | F60: Ministry | G60: Governanace, Administration & Digital Infrastructure | H60: PMU/PMC
A61: AB PMJAY Quality Certification Scheme | B61: PP00047 | C61: Pan India | D61: National Health Authority | E61: Ministry of Health and Family Welfare | F61: Ministry | G61: Governanace, Administration & Digital Infrastructure | H61: TPI/TPA/TPE/TPQA
A62: DIPAM | B62: PP00048 | C62: Pan India | E62: Ministry of Finance | F62: Ministry | G62: Financial Mgmt, Policy Analysis & Research | H62: Capacity building & Impact Assessment
A63: Extension of Study for Streamlining CPGRAMS, Department of Administrative Reforms and Public Grievances | B63: PP00049 | C63: Pan India | E63: Department of Administrative Reforms and Public Grievances | F63: Ministry | G63: Governanace, Administration & Digital Infrastructure | H63: Capacity building & Impact Assessment
A64: Startup Village Entrepreneurship Project | B64: PP00050 | C64: Pan India | E64: Ministry of Rural Development | F64: Ministry | G64: Social Welfare, Education & Skill Development | H64: TPI/TPA/TPE/TPQA
A65: ODF Workshop Kerela, Nagaland, Assam | B65: PP00051 | C65: Kerala, Nagaland, Assam | E65: Government of Kerala, Government of Nagaland, Government of Assam | F65: State Govt. | G65: Water & Sanitation | H65: Capacity building & Impact Assessment
A66: Third Party testing of Fisheries for presence of Added Formaldehyde in Fish | B66: PP00052 | C66: Goa | D66: Food and Drugs Authority | E66: Government of Goa | F66: State Govt. | G66: Agriculture, Food Processing & Supply Chain | H66: TPI/TPA/TPE/TPQA
A67: TPA of Coal Qualitative and Quantitative Analysis of Coal Supplied to SEMBCORP Energy India Limited (SEMBCORP) | B67: PP00053 | C67: Pan India | D67: SEMBCORP | F67: Corporate | G67: Mining & Metallurgy | H67: TPI/TPA/TPE/TPQA
A68: Confidential | B68: PP00054 | C68: Pan India | D68: Confidential | F68: Ministry | G68: Others | H68: Others
A69: GeM-Vendor Assessment | B69: PP00055 | C69: Pan India | D69: Government e-Marketplace | E69: Department for Promotion of Industry and Internal Trade | F69: Ministry | G69: Financial Mgmt, Policy Analysis & Research | H69: TPI/TPA/TPE/TPQA
A70: Kaya Kalp Certification for Private Hospitals (Pro Bono) | B70: PP00056 | C70: Pan India | E70: Ministry of Health and Family Welfare | F70: Ministry | G70: Governanace, Administration & Digital Infrastructure | H70: TPI/TPA/TPE/TPQA
A71: TPA of AIC & ATL - Atal Innovation Mission | B71: PP00057 | C71: Pan India | E71: NITI Aayog | F71: Ministry | G71: Social Welfare, Education & Skill Development | H71: TPI/TPA/TPE/TPQA
A72: TPA of Cleanliness of Railway Stations | B72: PP00058 | C72: Pan India | E72: Ministry of Railways | F72: Ministry | G72: Water & Sanitation | H72: TPI/TPA/TPE/TPQA
A73: MoRTH Excellence of Highways Awards 2019 | B73: PP00059 | C73: Pan India | E73: Ministry of Road Transport and Highways | F73: Ministry | G73: Governanace, Administration & Digital Infrastructure | H73: Capacity building & Impact Assessment
A74: Swachh UP(LOBs) | B74: PP00060 | C74: Uttar Pradesh | E74: Government of Uttar Pradesh | F74: State Govt. | G74: Water & Sanitation | H74: TPI/TPA/TPE/TPQA
A75: Assessment of Public & Community Toilets - SBM Urban, Govt of Maharashtra | B75: PP00061 | C75: Maharashtra | E75: Government of Maharashtra | F75: State Govt. | G75: Water & Sanitation | H75: TPI/TPA/TPE/TPQA
A76: Performance Audit of Solid Waste Management in ULBs, Govt of Haryana | B76: PP00062 | C76: Haryana | E76: Government of Haryana | F76: State Govt. | G76: Water & Sanitation | H76: TPI/TPA/TPE/TPQA
A77: Confidential | B77: PP00063 | C77: Pan India | D77: Confidential | F77: Ministry | G77: Others | H77: Others
A78: CAG PMU | B78: PP00064 | C78: Pan India | D78: Comptrollor and Auditor General of India | F78: Ministry | G78: Financial Mgmt, Policy Analysis & Research | H78: PMU/PMC
A79: Toy Testing Project (ProBono) | B79: PP00065 | C79: Pan India | E79: Department for Promotion of Industry and Internal Trade | F79: Ministry | G79: Others | H79: TPI/TPA/TPE/TPQA
A80: Economic Survey 2019-2020 Chapter | B80: PP00066 | C80: Pan India | E80: Ministry of Finance | F80: Ministry | G80: Financial Mgmt, Policy Analysis & Research | H80: Capacity building & Impact Assessment
A81: NPMPF (ProBono) | B81: PP00067 | C81: Pan India | E81: NITI Aayog | F81: Ministry | G81: Financial Mgmt, Policy Analysis & Research | H81: Capacity building & Impact Assessment
A82: TPA of National Initiative for Design Innovation | B82: PP00068 | C82: Pan India | E82: Ministry of Human Resource Development | F82: Ministry | G82: Social Welfare, Education & Skill Development | H82: TPI/TPA/TPE/TPQA
A83: TPA of TEQIP Phase III | B83: PP00069 | C83: Pan India | E83: Ministry of Human Resource Development | F83: Ministry | G83: Structural & Utilities Management | H83: TPI/TPA/TPE/TPQA
A84: LANCO ANPARA POWER LIMITED-PLANT END – LAPL | B84: PP00070 | C84: Uttar Pradesh | E84: LAPL | F84: Corporate | G84: Mining & Metallurgy | H84: TPI/TPA/TPE/TPQA
A85: Assessment for Swachhta Excellence Award 2019-20 | B85: PP00071 | C85: Pan India | E85: Ministry of Housing and Urban Affairs | F85: Ministry | G85: Water & Sanitation | H85: Capacity building & Impact Assessment
A86: Support for SUSV Excellence Award 2019-20 | B86: PP00072 | C86: Pan India | E86: Ministry of Housing and Urban Affairs | F86: Ministry | G86: Governanace, Administration & Digital Infrastructure | H86: Capacity building & Impact Assessment
A87: PMU for Policy Analysis, Research and Data Analytics | B87: PP00073 | C87: Pan India | E87: Ministry of Finance | F87: Ministry | G87: Financial Mgmt, Policy Analysis & Research | H87: Capacity building & Impact Assessment
A88: Census Survey of Water Body in Ganga Basin | B88: PP00074 | C88: Pan India | D88: National Mission for Clean Ganga | E88: Ministry of Jal Shakti | F88: Ministry | G88: Water & Sanitation | H88: TPI/TPA/TPE/TPQA
A89: Confidential | B89: PP00075 | C89: Pan India | D89: Confidential | F89: Ministry | G89: Others | H89: Others
A90: CIM | B90: PP00075/ PB00006 | C90: Pan India | G90: Financial Mgmt, Policy Analysis & Research | H90: Capacity building & Impact Assessment
A91: MHA CASU | B91: PP00076 | C91: Pan India | E91: Ministry of Home Affairs | F91: Ministry | G91: Financial Mgmt, Policy Analysis & Research | H91: Capacity building & Impact Assessment
A92: Ministry of Tourism PMU | B92: PP00077 | C92: Pan India | E92: Ministry of Tourism | F92: Ministry | G92: Arts, Culture & Tourism | H92: PMU/PMC
A93: Ministerial Policy and Implementation Dashboard | B93: PP00078 | C93: Pan India | E93: Ministry of Commerce and Industry & Others | F93: Ministry | G93: Governanace, Administration & Digital Infrastructure | H93: Capacity building & Impact Assessment
A94: Quality Assessment of Akash System at BDL Ltd | B94: PP00079 | C94: Pan India | D94: Defence Research and Developmenr Organisation | E94: Ministry of Defence | F94: Ministry | G94: Governanace, Administration & Digital Infrastructure | H94: TPI/TPA/TPE/TPQA
A95: DGFT Pulse Importer Facility Assessment | B95: PP00080 | C95: Pan India | D95: Department for Promotion of Industry and Internal Trade & Director General of Foreign Trade | E95: Ministry of Commerce and Industry | F95: Ministry | G95: Structural & Utilities Management | H95: TPI/TPA/TPE/TPQA
A96: Mapping of Products and Services on GeM Portal with HSN Code | B96: PP00081 | C96: Pan India | E96: Department for Promotion of Industry and Internal Trade | F96: Ministry | G96: Governanace, Administration & Digital Infrastructure | H96: Capacity building & Impact Assessment
A97: Audit of 20 RWC Terminals | B97: PP00082 | C97: Pan India | E97: Ministry of Railways | F97: Ministry | G97: Structural & Utilities Management | H97: Capacity building & Impact Assessment
A98: MoRTH Excellence of Highways Award 2020 | B98: PP00083 | C98: Pan India | E98: Ministry of Road Transport and Highways | F98: Ministry | G98: Governanace, Administration & Digital Infrastructure | H98: Capacity building & Impact Assessment
A99: Confidential | B99: PP00084 | C99: Pan India | D99: Confidential | F99: Ministry | G99: Others | H99: Others
A100: Swachh NDMC 2020-2021 | B100: PP00085 | C100: NCT of Delhi | D100: New Delhi Municipal Council | E100: Government of NCT of Delhi | F100: State Govt. | G100: Water & Sanitation | H100: TPI/TPA/TPE/TPQA
...
